Workbook

Sheet Export Worksheet
A1: MIDAS_NO | B1: BATCH_ID | C1: BATCH_NAME | D1: CREATED | E1: COMPLETED | F1: NUM_DATA_RECORDS_LOADED | G1: NUM_DATA_RECORDS_VALID | H1: NUM_DATA_RECORDS_ERRORED | I1: NUM_DATA_RECORDS_SKIPPED | J1: CREATED_BY | K1: MIDAS_NO | L1: STATUS | M1: On Tableau
A2: 010928M | B2: 34950 | C2: 603026 oct | D2: 13-10-2025 | E2: 13-10-2025 | F2: 1 | G2: 1 | H2: 0 | I2: 0 | J2: C192 | K2: 010928M | L2: COMPLETED | M2: =VLOOKUP(A2,'Tableau single and bulk'!A:B,2,FALSE) -> NEBAUTO
A3: 010931M | B3: 34937 | C3: Sept 2025 NEs | D3: 13-10-2025 | E3: 13-10-2025 | F3: 27 | G3: 27 | H3: 0 | I3: 0 | J3: Y337 | K3: 010931M | L3: COMPLETED | M3: =VLOOKUP(A3,'Tableau single and bulk'!A:B,2,FALSE) -> NEBAUTO
A4: 010991M | B4: 34916 | C4: Belvedere College | D4: 10-10-2025 | E4: 10-10-2025 | F4: 1 | G4: 1 | H4: 0 | I4: 0 | J4: X967 | K4: 010991M | L4: COMPLETED | M4: =VLOOKUP(A4,'Tableau single and bulk'!A:B,2,FALSE) -> NEBAUTO
A5: 010996M | B5: 34949 | C5: Sept 2025 NEs | D5: 13-10-2025 | E5: 13-10-2025 | F5: 66 | G5: 66 | H5: 0 | I5: 0 | J5: Y337 | K5: 010996M | L5: COMPLETED | M5: =VLOOKUP(A5,'Tableau single and bulk'!A:B,2,FALSE) -> NEBAUTO
A6: 010998M | B6: 34935 | C6: 2 Sept 2025 NEs | D6: 13-10-2025 | E6: 13-10-2025 | F6: 2 | G6: 2 | H6: 0 | I6: 0 | J6: Y337 | K6: 010998M | L6: COMPLETED | M6: =VLOOKUP(A6,'Tableau single and bulk'!A:B,2,FALSE) -> NEBAUTO
A7: 011007M | B7: 34940 | C7: Sept 2025 NEs | D7: 13-10-2025 | E7: 13-10-2025 | F7: 50 | G7: 50 | H7: 0 | I7: 0 | J7: Y337 | K7: 011007M | L7: COMPLETED | M7: =VLOOKUP(A7,'Tableau single and bulk'!A:B,2,FALSE) -> NEBAUTO
A8: 011040M | B8: 34943 | C8: 603616 1ne | D8: 13-10-2025 | E8: 13-10-2025 | F8: 1 | G8: 1 | H8: 0 | I8: 0 | J8: F243 | K8: 011040M | L8: COMPLETED | M8: =VLOOKUP(A8,'Tableau single and bulk'!A:B,2,FALSE) -> NEBAUTO
A9: 011045M | B9: 34843 | C9: Petrogas | D9: 08-10-2025 | E9: 08-10-2025 | F9: 1 | G9: 1 | H9: 0 | I9: 0 | J9: X967 | K9: 011045M | L9: COMPLETED | M9: =VLOOKUP(A9,'Tableau single and bulk'!A:B,2,FALSE) -> NEBAUTO
A10: 011053M | B10: 34846 | C10: Petrogas | D10: 08-10-2025 | E10: 08-10-2025 | F10: 1 | G10: 1 | H10: 0 | I10: 0 | J10: X967 | K10: 011053M | L10: COMPLETED | M10: =VLOOKUP(A10,'Tableau single and bulk'!A:B,2,FALSE) -> NEBAUTO
A11: 011054M | B11: 34909 | C11: 609862 | D11: 10-10-2025 | E11: 10-10-2025 | F11: 29 | G11: 29 | H11: 0 | I11: 0 | J11: J987 | K11: 011054M | L11: COMPLETED | M11: =VLOOKUP(A11,'Tableau single and bulk'!A:B,2,FALSE) -> NEBAUTO
A12: 011072M | B12: 34920 | C12: Cupa Operations | D12: 10-10-2025 | E12: 10-10-2025 | F12: 1 | G12: 1 | H12: 0 | I12: 0 | J12: X967 | K12: 011072M | L12: COMPLETED | M12: =VLOOKUP(A12,'Tableau single and bulk'!A:B,2,FALSE) -> NEBAUTO
A13: 011093M | B13: 34850 | C13: Capventis | D13: 08-10-2025 | E13: 08-10-2025 | F13: 1 | G13: 1 | H13: 0 | I13: 0 | J13: X967 | K13: 011093M | L13: COMPLETED | M13: =VLOOKUP(A13,'Tableau single and bulk'!A:B,2,FALSE) -> NEBAUTO
... A37: 011621M | B37: 34998 | C37: 2944 10 | D37: 14-10-2025 | E37: 14-10-2025 | F37: 1 | G37: 1 | H37: 0 | I37: 0 | J37: C192 | K37: 011621M | L37: COMPLETED | M37: =VLOOKUP(A37,'Tableau single and bulk'!A:B,2,FALSE) -> NEBAUTO
A38: 011637M | B38: 34934 | C38: 603782 48ne | D38: 13-10-2025 | E38: 13-10-2025 | F38: 48 | G38: 48 | H38: 0 | I38: 0 | J38: F243 | K38: 011637M | L38: COMPLETED | M38: =VLOOKUP(A38,'Tableau single and bulk'!A:B,2,FALSE) -> #N/A | N38: Archived
A39: 011697M | B39: 34973 | C39: 606901 1NE | D39: 14-10-2025 | E39: 14-10-2025 | F39: 1 | G39: 1 | H39: 0 | I39: 0 | J39: F243 | K39: 011697M | L39: COMPLETED | M39: =VLOOKUP(A39,'Tableau single and bulk'!A:B,2,FALSE) -> NEBAUTO
A40: 011703M | B40: 34997 | C40: 602254 | D40: 14-10-2025 | E40: 14-10-2025 | F40: 13 | G40: 13 | H40: -12 | I40: 12 | J40: J905 | K40: 011703M | L40: COMPLETED | M40: =VLOOKUP(A40,'Tableau single and bulk'!A:B,2,FALSE) -> NEBAUTO
A41: 011722M | B41: 35006 | C41: Opening HR Limited | D41: 14-10-2025 | E41: 14-10-2025 | F41: 1 | G41: 1 | H41: 0 | I41: 0 | J41: X967 | K41: 011722M | L41: COMPLETED | M41: =VLOOKUP(A41,'Tableau single and bulk'!A:B,2,FALSE) -> NEBAUTO
A42: 011920M | B42: 34968 | C42: Eimear Doyle | D42: 14-10-2025 | E42: 14-10-2025 | F42: 1 | G42: 1 | H42: 0 | I42: 0 | J42: Y337 | K42: 011920M | L42: COMPLETED | M42: =VLOOKUP(A42,'Tableau single and bulk'!A:B,2,FALSE) -> NEBAUTO
A43: 011928M | B43: 35023 | C43: Oct 2025 NEs | D43: 15-10-2025 | E43: 15-10-2025 | F43: 31 | G43: 31 | H43: 0 | I43: 0 | J43: Y337 | K43: 011928M | L43: COMPLETED | M43: =VLOOKUP(A43,'Tableau single and bulk'!A:B,2,FALSE) -> NEBAUTO
A44: 011943M | B44: 35012 | C44: Gowan Group Ltd | D44: 15-10-2025 | E44: 15-10-2025 | F44: 3 | G44: 3 | H44: -1 | I44: 1 | J44: X967 | K44: 011943M | L44: COMPLETED | M44: =VLOOKUP(A44,'Tableau single and bulk'!A:B,2,FALSE) -> NEBAUTO
A45: 011946M | B45: 35019 | C45: 606866 Ne Bulk | D45: 15-10-2025 | E45: 15-10-2025 | F45: 4 | G45: 4 | H45: 0 | I45: 0 | J45: J905 | K45: 011946M | L45: COMPLETED | M45: =VLOOKUP(A45,'Tableau single and bulk'!A:B,2,FALSE) -> NEBAUTO
A46: 011956M | B46: 34911 | C46: Agri Health | D46: 10-10-2025 | E46: 10-10-2025 | F46: 3 | G46: 3 | H46: 0 | I46: 0 | J46: X967 | K46: 011956M | L46: COMPLETED | M46: =VLOOKUP(A46,'Tableau single and bulk'!A:B,2,FALSE) -> NEBAUTO
A47: 011958M | B47: 35032 | C47: x27 NEs 15102025 | D47: 15-10-2025 | E47: 15-10-2025 | F47: 27 | G47: 27 | H47: -1 | I47: 1 | J47: H506 | K47: 011958M | L47: COMPLETED | M47: =VLOOKUP(A47,'Tableau single and bulk'!A:B,2,FALSE) -> NEBAUTO
A48: 011972M | B48: 35020 | C48: Magnet Networks | D48: 15-10-2025 | E48: 15-10-2025 | F48: 1 | G48: 1 | H48: 0 | I48: 0 | J48: X967 | K48: 011972M | L48: COMPLETED | M48: =VLOOKUP(A48,'Tableau single and bulk'!A:B,2,FALSE) -> NEBAUTO
A49: 011988M | B49: 35039 | C49: 606840 oct | D49: 15-10-2025 | E49: 15-10-2025 | F49: 7 | G49: 7 | H49: -3 | I49: 3 | J49: C192 | K49: 011988M | L49: COMPLETED | M49: =VLOOKUP(A49,'Tableau single and bulk'!A:B,2,FALSE) -> NEBAUTO
A50: 011991M | B50: 34970 | C50: Laura Farrell | D50: 14-10-2025 | E50: 14-10-2025 | F50: 1 | G50: 1 | H50: 0 | I50: 0 | J50: Y337 | K50: 011991M | L50: COMPLETED | M50: =VLOOKUP(A50,'Tableau single and bulk'!A:B,2,FALSE) -> NEBAUTO
... A642: O423996 | B642: 35559 | C642: 602334 Firhouse | D642: 29-10-2025 | E642: 29-10-2025 | F642: 3 | G642: 3 | H642: 0 | I642: 0 | J642: F243 | K642: O423996 | L642: COMPLETED | M642: =VLOOKUP(A642,'Tableau single and bulk'!A:B,2,FALSE) -> #N/A
A643: O424006 | B643: 35560 | C643: 602334 Hermitage | D643: 29-10-2025 | E643: 29-10-2025 | F643: 7 | G643: 7 | H643: 0 | I643: 0 | J643: F243 | K643: O424006 | L643: COMPLETED | M643: =VLOOKUP(A643,'Tableau single and bulk'!A:B,2,FALSE) -> #N/A | N643: completed in Nov
A644: O426025 | B644: 35581 | C644: Bord na Mona | D644: 30-10-2025 | E644: 30-10-2025 | F644: 3 | G644: 3 | H644: 0 | I644: 0 | J644: X967 | K644: O426025 | L644: COMPLETED | M644: =VLOOKUP(A644,'Tableau single and bulk'!A:B,2,FALSE) -> NEBAUTO

Sheet Sheet2
A3: Row Labels | B3: Count of Bulk Numbers Loaded
B4: 1
A5: NEBAUTO | B5: 294
A6: NESAUTO | B6: 224
A7: #N/A | B7: 8
A8: (blank)
A9: Grand Total | B9: 527

Sheet IP_Org_Usecase_Submission_Statu
A1: MIDAS_NO | B1: Organization Name | C1: Use Case Name | D1: Submission Date and Time (UTC) | E1: Reference Number | F1: Submission Status | G1: Organization Status | H1: Bulk Numbers Loaded | I1: Bulk or Single WI | J1: Comments | K1: Completed | L1: Scheme Number | M1: Scheme Name
A2: 010921M | B2: eircom | C2: Add Members | D2: 2025-10-13 13:14:11.903000Z | E2: 010921M | F2: Completed | G2: Active | H2: =VLOOKUP(A2,'Export Worksheet'!A:L,6,FALSE) -> #N/A | I2: =VLOOKUP(A2,'Tableau single and bulk'!A:B,2,FALSE) -> NESAUTO | K2: =VLOOKUP(A2,'Tableau single and bulk'!A:I,9,FALSE) -> 45943.593 | L2: =VLOOKUP(A2,'Tableau single and bulk'!A:L,12,FALSE) -> 603757 | M2: =VLOOKUP(A2,'Tableau single and bulk'!A:AA,27,FALSE) -> eircom Limited AVC Scheme
A3: 010928M | B3: Vestas Ireland Limited | C3: Add Members | D3: 2025-10-13 14:26:34.155000Z | E3: 010928M | F3: Completed | G3: Active | H3: =VLOOKUP(A3,'Export Worksheet'!A:L,6,FALSE) -> 1 | I3: =VLOOKUP(A3,'Tableau single and bulk'!A:B,2,FALSE) -> NEBAUTO | K3: =VLOOKUP(A3,'Tableau single and bulk'!A:I,9,FALSE) -> 45943.643 | L3: =VLOOKUP(A3,'Tableau single and bulk'!A:L,12,FALSE) -> 603026 | M3: =VLOOKUP(A3,'Tableau single and bulk'!A:AA,27,FALSE) -> Vestas Ireland Limited
A4: 010931M | B4: Kerry Group Plc | C4: Add Members | D4: 2025-10-13 11:20:00.790000Z | E4: 010931M | F4: Completed | G4: Active | H4: =VLOOKUP(A4,'Export Worksheet'!A:L,6,FALSE) -> 27 | I4: =VLOOKUP(A4,'Tableau single and bulk'!A:B,2,FALSE) -> NEBAUTO | K4: =VLOOKUP(A4,'Tableau single and bulk'!A:I,9,FALSE) -> 45943.514 | L4: =VLOOKUP(A4,'Tableau single and bulk'!A:L,12,FALSE) -> 605376 | M4: =VLOOKUP(A4,'Tableau single and bulk'!A:AA,27,FALSE) -> Kerry Dairy Holdings (Ireland) Limited
A5: 010991M | B5: Joseph G Byrne and Sons Consulting Actuaries | C5: Add Members | D5: 2025-10-10 14:44:33.244000Z | E5: 010991M | F5: Completed | G5: Active | H5: =VLOOKUP(A5,'Export Worksheet'!A:L,6,FALSE) -> 1 | I5: =VLOOKUP(A5,'Tableau single and bulk'!A:B,2,FALSE) -> NEBAUTO | K5: =VLOOKUP(A5,'Tableau single and bulk'!A:I,9,FALSE) -> 45940.656 | L5: =VLOOKUP(A5,'Tableau single and bulk'!A:L,12,FALSE) -> 609763 | M5: =VLOOKUP(A5,'Tableau single and bulk'!A:AA,27,FALSE) -> Belvedere College SJ
A6: 010996M | B6: Stryker Ireland | C6: Add Members | D6: 2025-10-13 14:08:22.973000Z | E6: 010996M | F6: Completed | G6: Active | H6: =VLOOKUP(A6,'Export Worksheet'!A:L,6,FALSE) -> 66 | I6: =VLOOKUP(A6,'Tableau single and bulk'!A:B,2,FALSE) -> NEBAUTO | K6: =VLOOKUP(A6,'Tableau single and bulk'!A:I,9,FALSE) -> 45943.631 | L6: =VLOOKUP(A6,'Tableau single and bulk'!A:L,12,FALSE) -> 603990 | M6: =VLOOKUP(A6,'Tableau single and bulk'!A:AA,27,FALSE) -> Stryker Ireland DC Pension Plan
A7: 010998M | B7: Stryker Ireland | C7: Add Members | D7: 2025-10-13 10:53:45.084000Z | E7: 010998M | F7: Completed | G7: Active | H7: =VLOOKUP(A7,'Export Worksheet'!A:L,6,FALSE) -> 2 | I7: =VLOOKUP(A7,'Tableau single and bulk'!A:B,2,FALSE) -> NEBAUTO | K7: =VLOOKUP(A7,'Tableau single and bulk'!A:I,9,FALSE) -> 45943.496 | L7: =VLOOKUP(A7,'Tableau single and bulk'!A:L,12,FALSE) -> 602167 | M7: =VLOOKUP(A7,'Tableau single and bulk'!A:AA,27,FALSE) -> Stryker Ireland Limited Pension Scheme
A8: 011003M | B8: PHX Ireland Group Limited | C8: Add Members | D8: 2025-10-09 19:52:22.884000Z | E8: 011003M | F8: Completed | G8: Active | H8: =VLOOKUP(A8,'Export Worksheet'!A:L,6,FALSE) -> #N/A | I8: =VLOOKUP(A8,'Tableau single and bulk'!A:B,2,FALSE) -> NESAUTO | K8: =VLOOKUP(A8,'Tableau single and bulk'!A:I,9,FALSE) -> 45939.87 | L8: =VLOOKUP(A8,'Tableau single and bulk'!A:L,12,FALSE) -> 609838 | M8: =VLOOKUP(A8,'Tableau single and bulk'!A:AA,27,FALSE) -> PHX Ireland Group Limited
A9: 011007M | B9: Kerry Group Plc | C9: Add Members | D9: 2025-10-13 11:53:50.392000Z | E9: 011007M | F9: Completed | G9: Active | H9: =VLOOKUP(A9,'Export Worksheet'!A:L,6,FALSE) -> 50 | I9: =VLOOKUP(A9,'Tableau single and bulk'!A:B,2,FALSE) -> NEBAUTO | K9: =VLOOKUP(A9,'Tableau single and bulk'!A:I,9,FALSE) -> 45943.537 | L9: =VLOOKUP(A9,'Tableau single and bulk'!A:L,12,FALSE) -> 603888 | M9: =VLOOKUP(A9,'Tableau single and bulk'!A:AA,27,FALSE) -> Kerry Group Plc
A10: 011018M | B10: Aon | C10: Add Members | D10: 2025-10-10 16:28:04.193000Z | E10: 011018M | F10: Completed | G10: Active | H10: =VLOOKUP(A10,'Export Worksheet'!A:L,6,FALSE) -> #N/A | I10: =VLOOKUP(A10,'Tableau single and bulk'!A:B,2,FALSE) -> NESAUTO | K10: =VLOOKUP(A10,'Tableau single and bulk'!A:I,9,FALSE) -> 45940.728 | L10: =VLOOKUP(A10,'Tableau single and bulk'!A:L,12,FALSE) -> 609805 | M10: =VLOOKUP(A10,'Tableau single and bulk'!A:AA,27,FALSE) -> Aztec Financial Services (Irl) Limited
A11: 011019M | B11: Aon | C11: Add Members | D11: 2025-10-13 08:54:47.413000Z | E11: 011019M | F11: Completed | G11: Active | H11: =VLOOKUP(A11,'Export Worksheet'!A:L,6,FALSE) -> #N/A | I11: =VLOOKUP(A11,'Tableau single and bulk'!A:B,2,FALSE) -> NESAUTO | K11: =VLOOKUP(A11,'Tableau single and bulk'!A:I,9,FALSE) -> 45943.413 | L11: =VLOOKUP(A11,'Tableau single and bulk'!A:L,12,FALSE) -> 609805 | M11: =VLOOKUP(A11,'Tableau single and bulk'!A:AA,27,FALSE) -> Aztec Financial Services (Irl) Limited
A12: 011021M | B12: Unio Employee Benefits | C12: Add Members | D12: 2025-10-13 11:01:28.096000Z | E12: 011021M | F12: Completed | G12: Active | H12: =VLOOKUP(A12,'Export Worksheet'!A:L,6,FALSE) -> #N/A | I12: =VLOOKUP(A12,'Tableau single and bulk'!A:B,2,FALSE) -> NESAUTO | K12: =VLOOKUP(A12,'Tableau single and bulk'!A:I,9,FALSE) -> 45943.501 | L12: =VLOOKUP(A12,'Tableau single and bulk'!A:L,12,FALSE) -> 603261 | M12: =VLOOKUP(A12,'Tableau single and bulk'!A:AA,27,FALSE) -> Euler Hermes Services Ireland Ltd
A13: 011040M | B13: Irish Life | C13: Add Members | D13: 2025-10-13 14:56:26.403000Z | E13: 011040M | F13: Completed | G13: Active | H13: =VLOOKUP(A13,'Export Worksheet'!A:L,6,FALSE) -> 1 | I13: =VLOOKUP(A13,'Tableau single and bulk'!A:B,2,FALSE) -> NEBAUTO | K13: =VLOOKUP(A13,'Tableau single and bulk'!A:I,9,FALSE) -> 45943.664 | L13: =VLOOKUP(A13,'Tableau single and bulk'!A:L,12,FALSE) -> 603616 | M13: =VLOOKUP(A13,'Tableau single and bulk'!A:AA,27,FALSE) -> Google Ireland Limited
A14: 011045M | B14: Irish Life | C14: Add Members | D14: 2025-10-08 13:58:50.820000Z | E14: 011045M | F14: Completed | G14: Active | H14: =VLOOKUP(A14,'Export Worksheet'!A:L,6,FALSE) -> 1 | I14: =VLOOKUP(A14,'Tableau single and bulk'!A:B,2,FALSE) -> NEBAUTO | K14: =VLOOKUP(A14,'Tableau single and bulk'!A:I,9,FALSE) -> 45938.624 | L14: =VLOOKUP(A14,'Tableau single and bulk'!A:L,12,FALSE) -> 603640 | M14: =VLOOKUP(A14,'Tableau single and bulk'!A:AA,27,FALSE) -> Petrogas Group Limited
A15: 011049M | B15: Irish Life | C15: Add Members | D15: 2025-10-10 09:34:21.060000Z | E15: 011049M | F15: Completed | G15: Active | H15: =VLOOKUP(A15,'Export Worksheet'!A:L,6,FALSE) -> #N/A | I15: =VLOOKUP(A15,'Tableau single and bulk'!A:B,2,FALSE) -> NEBAUTO | K15: =VLOOKUP(A15,'Tableau single and bulk'!A:I,9,FALSE) -> 45940.44 | L15: =VLOOKUP(A15,'Tableau single and bulk'!A:L,12,FALSE) -> 608020 | M15: =VLOOKUP(A15,'Tableau single and bulk'!A:AA,27,FALSE) -> Renaissance Services of Europe Limited | N15: Batch was deleted
A16: 011053M | B16: Irish Life | C16: Add Members | D16: 2025-10-08 14:02:42.025000Z | E16: 011053M | F16: Completed | G16: Active | H16: =VLOOKUP(A16,'Export Worksheet'!A:L,6,FALSE) -> 1 | I16: =VLOOKUP(A16,'Tableau single and bulk'!A:B,2,FALSE) -> NEBAUTO | K16: =VLOOKUP(A16,'Tableau single and bulk'!A:I,9,FALSE) -> 45938.627 | L16: =VLOOKUP(A16,'Tableau single and bulk'!A:L,12,FALSE) -> 603640 | M16: =VLOOKUP(A16,'Tableau single and bulk'!A:AA,27,FALSE) -> Petrogas Group Limited
A17: 011054M | B17: Irish Life | C17: Add Members | D17: 2025-10-10 11:03:47.641000Z | E17: 011054M | F17: Completed | G17: Active | H17: =VLOOKUP(A17,'Export Worksheet'!A:L,6,FALSE) -> 29 | I17: =VLOOKUP(A17,'Tableau single and bulk'!A:B,2,FALSE) -> NEBAUTO | K17: =VLOOKUP(A17,'Tableau single and bulk'!A:I,9,FALSE) -> 45940.503 | L17: =VLOOKUP(A17,'Tableau single and bulk'!A:L,12,FALSE) -> 609862 | M17: =VLOOKUP(A17,'Tableau single and bulk'!A:AA,27,FALSE) -> Dunnes Stores Unlimited Company
A18: 011071M | B18: Aon | C18: Add Members | D18: 2025-10-13 10:48:52.266000Z | E18: 011071M | F18: Completed | G18: Active | H18: =VLOOKUP(A18,'Export Worksheet'!A:L,6,FALSE) -> #N/A | I18: =VLOOKUP(A18,'Tableau single and bulk'!A:B,2,FALSE) -> NESAUTO | K18: =VLOOKUP(A18,'Tableau single and bulk'!A:I,9,FALSE) -> 45943.492 | L18: =VLOOKUP(A18,'Tableau single and bulk'!A:L,12,FALSE) -> 609844 | M18: =VLOOKUP(A18,'Tableau single and bulk'!A:AA,27,FALSE) -> Kitman Labs Limited
A19: 011072M | B19: Coupa Operations Inc | C19: Add Members | D19: 2025-10-10 16:18:16.800000Z | E19: 011072M | F19: Completed | G19: Active | H19: =VLOOKUP(A19,'Export Worksheet'!A:L,6,FALSE) -> 1 | I19: =VLOOKUP(A19,'Tableau single and bulk'!A:B,2,FALSE) -> NEBAUTO | K19: =VLOOKUP(A19,'Tableau single and bulk'!A:I,9,FALSE) -> 45940.721 | L19: =VLOOKUP(A19,'Tableau single and bulk'!A:L,12,FALSE) -> 603485 | M19: =VLOOKUP(A19,'Tableau single and bulk'!A:AA,27,FALSE) -> Coupa Operations Inc.
A20: 011088M | B20: Munster Cattle Breeding Group Ltd | C20: Add Members | D20: 2025-10-13 10:40:24.006000Z | E20: 011088M | F20: Completed | G20: Active | H20: =VLOOKUP(A20,'Export Worksheet'!A:L,6,FALSE) -> #N/A | I20: =VLOOKUP(A20,'Tableau single and bulk'!A:B,2,FALSE) -> NESAUTO | K20: =VLOOKUP(A20,'Tableau single and bulk'!A:I,9,FALSE) -> 45943.486 | L20: =VLOOKUP(A20,'Tableau single and bulk'!A:L,12,FALSE) -> 602712 | M20: =VLOOKUP(A20,'Tableau single and bulk'!A:AA,27,FALSE) -> MUNSTER CATTLE BREEDING GROUP LTD
A21: 011093M | B21: Irish Life | C21: Add Members | D21: 2025-10-08 14:42:15.155000Z | E21: 011093M | F21: Completed | G21: Active | H21: =VLOOKUP(A21,'Export Worksheet'!A:L,6,FALSE) -> 1 | I21: =VLOOKUP(A21,'Tableau single and bulk'!A:B,2,FALSE) -> NEBAUTO | K21: =VLOOKUP(A21,'Tableau single and bulk'!A:I,9,FALSE) -> 45938.654 | L21: =VLOOKUP(A21,'Tableau single and bulk'!A:L,12,FALSE) -> 603914 | M21: =VLOOKUP(A21,'Tableau single and bulk'!A:AA,27,FALSE) -> Capventis Limited
A22: 011105M | B22: Paddy Denby Engineering Ltd | C22: Add Members | D22: 2025-10-16 13:31:31.639000Z | E22: 011105M | F22: Completed | G22: Active | H22: =VLOOKUP(A22,'Export Worksheet'!A:L,6,FALSE) -> 6 | I22: =VLOOKUP(A22,'Tableau single and bulk'!A:B,2,FALSE) -> NEBAUTO | K22: =VLOOKUP(A22,'Tableau single and bulk'!A:I,9,FALSE) -> 45946.605 | L22: =VLOOKUP(A22,'Tableau single and bulk'!A:L,12,FALSE) -> 601157 | M22: =VLOOKUP(A22,'Tableau single and bulk'!A:AA,27,FALSE) -> Paddy Denby Engineering Ltd
A23: 011109M | B23: WTW | C23: Add Members | D23: 2025-10-10 09:55:27.962000Z | E23: 011109M | F23: Completed | G23: Active | H23: =VLOOKUP(A23,'Export Worksheet'!A:L,6,FALSE) -> 1 | I23: =VLOOKUP(A23,'Tableau single and bulk'!A:B,2,FALSE) -> NEBAUTO | K23: =VLOOKUP(A23,'Tableau single and bulk'!A:I,9,FALSE) -> 45940.455 | L23: =VLOOKUP(A23,'Tableau single and bulk'!A:L,12,FALSE) -> 602420 | M23: =VLOOKUP(A23,'Tableau single and bulk'!A:AA,27,FALSE) -> Netgear International Limited
A24: 011140M | B24: Irish Life | C24: Add Members | D24: 2025-10-13 14:00:06.147000Z | E24: 011140M | F24: Completed | G24: Active | H24: =VLOOKUP(A24,'Export Worksheet'!A:L,6,FALSE) -> #N/A | I24: =VLOOKUP(A24,'Tableau single and bulk'!A:B,2,FALSE) -> NEBAUTO | K24: =VLOOKUP(A24,'Tableau single and bulk'!A:I,9,FALSE) -> 45943.625 | L24: =VLOOKUP(A24,'Tableau single and bulk'!A:L,12,FALSE) -> 603524 | M24: =VLOOKUP(A24,'Tableau single and bulk'!A:AA,27,FALSE) -> Riot Games Limited | N24: Nothing loaded | O24: hard to follow from Midas what happened - Multiple Bulk Items created
A25: 011154M | B25: Veolia UK and Ireland | C25: Add Members | D25: 2025-10-10 10:50:01.254000Z | E25: 011154M | F25: Completed | G25: Active | H25: =VLOOKUP(A25,'Export Worksheet'!A:L,6,FALSE) -> 9 | I25: =VLOOKUP(A25,'Tableau single and bulk'!A:B,2,FALSE) -> NEBAUTO | K25: =VLOOKUP(A25,'Tableau single and bulk'!A:I,9,FALSE) -> 45940.493 | L25: =VLOOKUP(A25,'Tableau single and bulk'!A:L,12,FALSE) -> 602377 | M25: =VLOOKUP(A25,'Tableau single and bulk'!A:AA,27,FALSE) -> Veolia Energy Ser Ireland Ltd
A26: 011155M | B26: Lockton Employee Benefits Ireland | C26: Add Members | D26: 2025-10-13 10:24:20.642000Z | E26: 011155M | F26: Completed | G26: Active | H26: =VLOOKUP(A26,'Export Worksheet'!A:L,6,FALSE) -> #N/A | I26: =VLOOKUP(A26,'Tableau single and bulk'!A:B,2,FALSE) -> NESAUTO | K26: =VLOOKUP(A26,'Tableau single and bulk'!A:I,9,FALSE) -> 45943.475 | L26: =VLOOKUP(A26,'Tableau single and bulk'!A:L,12,FALSE) -> 603651 | M26: =VLOOKUP(A26,'Tableau single and bulk'!A:AA,27,FALSE) -> Specialist Technical Engineering Serv.
A27: 011159M | B27: Irish Life | C27: Add Members | D27: 2025-10-08 17:22:23.724000Z | E27: 011159M | F27: Completed | G27: Active | H27: =VLOOKUP(A27,'Export Worksheet'!A:L,6,FALSE) -> 24 | I27: =VLOOKUP(A27,'Tableau single and bulk'!A:B,2,FALSE) -> NEBAUTO | K27: =VLOOKUP(A27,'Tableau single and bulk'!A:I,9,FALSE) -> 45938.765 | L27: =VLOOKUP(A27,'Tableau single and bulk'!A:L,12,FALSE) -> 603358 | M27: =VLOOKUP(A27,'Tableau single and bulk'!A:AA,27,FALSE) -> Arachas Corporate Brokers Ltd
A28: 011192M | B28: Cathedral Financial Consultants Ltd | C28: Add Members | D28: 2025-10-13 15:10:47.193000Z | E28: 011192M | F28: Completed | G28: Active | H28: =VLOOKUP(A28,'Export Worksheet'!A:L,6,FALSE) -> 17 | I28: =VLOOKUP(A28,'Tableau single and bulk'!A:B,2,FALSE) -> NEBAUTO | K28: =VLOOKUP(A28,'Tableau single and bulk'!A:I,9,FALSE) -> 45943.674 | L28: =VLOOKUP(A28,'Tableau single and bulk'!A:L,12,FALSE) -> 603578 | M28: =VLOOKUP(A28,'Tableau single and bulk'!A:AA,27,FALSE) -> Vow Europe Limited
A29: 011335M | B29: Castlehitt Limited | C29: Add Members | D29: 2025-10-13 14:19:32.375000Z | E29: 011335M | F29: Completed | G29: Active | H29: =VLOOKUP(A29,'Export Worksheet'!A:L,6,FALSE) -> #N/A | I29: =VLOOKUP(A29,'Tableau single and bulk'!A:B,2,FALSE) -> NESAUTO | K29: =VLOOKUP(A29,'Tableau single and bulk'!A:I,9,FALSE) -> 45943.638 | L29: =VLOOKUP(A29,'Tableau single and bulk'!A:L,12,FALSE) -> 605381 | M29: =VLOOKUP(A29,'Tableau single and bulk'!A:AA,27,FALSE) -> Castlehitt Limited
A30: 011341M | B30: Beacon Hospital Sandyford Limited | C30: Add Members | D30: 2025-10-14 11:23:32.269000Z | E30: 011341M | F30: Completed | G30: Active | H30: =VLOOKUP(A30,'Export Worksheet'!A:L,6,FALSE) -> 22 | I30: =VLOOKUP(A30,'Tableau single and bulk'!A:B,2,FALSE) -> NEBAUTO | K30: =VLOOKUP(A30,'Tableau single and bulk'!A:I,9,FALSE) -> 45944.516 | L30: =VLOOKUP(A30,'Tableau single and bulk'!A:L,12,FALSE) -> 602375 | M30: =VLOOKUP(A30,'Tableau single and bulk'!A:AA,27,FALSE) -> Beacon Hospital
A31: 011352M | B31: Brown Thomas and Co Limited | C31: Add Members | D31: 2025-10-14 14:43:18.308000Z | E31: 011352M | F31: Completed | G31: Active | H31: =VLOOKUP(A31,'Export Worksheet'!A:L,6,FALSE) -> 5 | I31: =VLOOKUP(A31,'Tableau single and bulk'!A:B,2,FALSE) -> NEBAUTO | K31: =VLOOKUP(A31,'Tableau single and bulk'!A:I,9,FALSE) -> 45944.655 | L31: =VLOOKUP(A31,'Tableau single and bulk'!A:L,12,FALSE) -> 602903 | M31: =VLOOKUP(A31,'Tableau single and bulk'!A:AA,27,FALSE) -> Brown Thomas Arnotts Limited
A32: 011355M | B32: Patrick J Tobin Ltd | C32: Add Members | D32: 2025-10-11 10:21:39.372000Z | E32: 011355M | F32: Completed | G32: Active | H32: =VLOOKUP(A32,'Export Worksheet'!A:L,6,FALSE) -> #N/A | I32: =VLOOKUP(A32,'Tableau single and bulk'!A:B,2,FALSE) -> NESAUTO | K32: =VLOOKUP(A32,'Tableau single and bulk'!A:I,9,FALSE) -> 45941.473 | L32: =VLOOKUP(A32,'Tableau single and bulk'!A:L,12,FALSE) -> 602944 | M32: =VLOOKUP(A32,'Tableau single and bulk'!A:AA,27,FALSE) -> PATRICK J TOBIN LTD
A33: 011356M | B33: Patrick J Tobin Ltd | C33: Add Members | D33: 2025-10-11 10:17:43.024000Z | E33: 011356M | F33: Completed | G33: Active | H33: =VLOOKUP(A33,'Export Worksheet'!A:L,6,FALSE) -> #N/A | I33: =VLOOKUP(A33,'Tableau single and bulk'!A:B,2,FALSE) -> NESAUTO | K33: =VLOOKUP(A33,'Tableau single and bulk'!A:I,9,FALSE) -> 45941.471 | L33: =VLOOKUP(A33,'Tableau single and bulk'!A:L,12,FALSE) -> 602944 | M33: =VLOOKUP(A33,'Tableau single and bulk'!A:AA,27,FALSE) -> PATRICK J TOBIN LTD
A34: 011357M | B34: Patrick J Tobin Ltd | C34: Add Members | D34: 2025-10-11 10:20:48.880000Z | E34: 011357M | F34: Completed | G34: Active | H34: =VLOOKUP(A34,'Export Worksheet'!A:L,6,FALSE) -> #N/A | I34: =VLOOKUP(A34,'Tableau single and bulk'!A:B,2,FALSE) -> NESAUTO | K34: =VLOOKUP(A34,'Tableau single and bulk'!A:I,9,FALSE) -> 45941.473 | L34: =VLOOKUP(A34,'Tableau single and bulk'!A:L,12,FALSE) -> 602944 | M34: =VLOOKUP(A34,'Tableau single and bulk'!A:AA,27,FALSE) -> PATRICK J TOBIN LTD
A35: 011358M | B35: Patrick J Tobin Ltd | C35: Add Members | D35: 2025-10-11 09:42:59.881000Z | E35: 011358M | F35: Completed | G35: Active | H35: =VLOOKUP(A35,'Export Worksheet'!A:L,6,FALSE) -> #N/A | I35: =VLOOKUP(A35,'Tableau single and bulk'!A:B,2,FALSE) -> NESAUTO | K35: =VLOOKUP(A35,'Tableau single and bulk'!A:I,9,FALSE) -> 45941.446 | L35: =VLOOKUP(A35,'Tableau single and bulk'!A:L,12,FALSE) -> 602944 | M35: =VLOOKUP(A35,'Tableau single and bulk'!A:AA,27,FALSE) -> PATRICK J TOBIN LTD
A36: 011359M | B36: Apleona Ireland Limited | C36: Add Members | D36: 2025-10-13 10:52:44.481000Z | E36: 011359M | F36: Completed | G36: Active | H36: =VLOOKUP(A36,'Export Worksheet'!A:L,6,FALSE) -> 1 | I36: =VLOOKUP(A36,'Tableau single and bulk'!A:B,2,FALSE) -> NEBAUTO | K36: =VLOOKUP(A36,'Tableau single and bulk'!A:I,9,FALSE) -> 45943.495 | L36: =VLOOKUP(A36,'Tableau single and bulk'!A:L,12,FALSE) -> 606934 | M36: =VLOOKUP(A36,'Tableau single and bulk'!A:AA,27,FALSE) -> Apleona Ireland Limited
... A41: 011391M | B41: Roadstone Limited | C41: Add Members | D41: 2025-10-13 09:42:16.436000Z | E41: 011391M | F41: Completed | G41: Active | H41: =VLOOKUP(A41,'Export Worksheet'!A:L,6,FALSE) -> #N/A | I41: =VLOOKUP(A41,'Tableau single and bulk'!A:B,2,FALSE) -> NESAUTO | K41: =VLOOKUP(A41,'Tableau single and bulk'!A:I,9,FALSE) -> 45943.446 | L41: =VLOOKUP(A41,'Tableau single and bulk'!A:L,12,FALSE) -> 602719 | M41: =VLOOKUP(A41,'Tableau single and bulk'!A:AA,27,FALSE) -> Roadstone Limited
A42: 011392M | B42: Irish Life | C42: Add Members | D42: 2025-10-14 09:35:08.886000Z | E42: 011392M | F42: Completed | G42: Active | H42: =VLOOKUP(A42,'Export Worksheet'!A:L,6,FALSE) -> #N/A | I42: =VLOOKUP(A42,'Tableau single and bulk'!A:B,2,FALSE) -> NEBAUTO | K42: =VLOOKUP(A42,'Tableau single and bulk'!A:I,9,FALSE) -> 45944.441 | L42: =VLOOKUP(A42,'Tableau single and bulk'!A:L,12,FALSE) -> 603783 | M42: =VLOOKUP(A42,'Tableau single and bulk'!A:AA,27,FALSE) -> Kverneland Group Ireland Limited | N42: errors found
A43: 011396M | B43: Irish Life | C43: Add Members | D43: 2025-10-15 08:18:04.397000Z | E43: 011396M | F43: Completed | G43: Active | H43: =VLOOKUP(A43,'Export Worksheet'!A:L,6,FALSE) -> 7 | I43: =VLOOKUP(A43,'Tableau single and bulk'!A:B,2,FALSE) -> NEBAUTO | K43: =VLOOKUP(A43,'Tableau single and bulk'!A:I,9,FALSE) -> 45945.387 | L43: =VLOOKUP(A43,'Tableau single and bulk'!A:L,12,FALSE) -> 609743 | M43: =VLOOKUP(A43,'Tableau single and bulk'!A:AA,27,FALSE) -> Motorola Solutions UK Ltd (Irl Branch)
A44: 011400M | B44: Irish Life | C44: Add Members | D44: 2025-10-09 10:10:19.998000Z | E44: 011400M | F44: Completed | G44: Active | H44: =VLOOKUP(A44,'Export Worksheet'!A:L,6,FALSE) -> 3 | I44: =VLOOKUP(A44,'Tableau single and bulk'!A:B,2,FALSE) -> NEBAUTO | K44: =VLOOKUP(A44,'Tableau single and bulk'!A:I,9,FALSE) -> 45939.465 | L44: =VLOOKUP(A44,'Tableau single and bulk'!A:L,12,FALSE) -> 603612 | M44: =VLOOKUP(A44,'Tableau single and bulk'!A:AA,27,FALSE) -> Stauntons Pharmacy Limited
A45: 011406M | B45: Irish Life | C45: Add Members | D45: 2025-10-15 08:18:40.037000Z | E45: 011406M | F45: Completed | G45: Active | H45: =VLOOKUP(A45,'Export Worksheet'!A:L,6,FALSE) -> 1 | I45: =VLOOKUP(A45,'Tableau single and bulk'!A:B,2,FALSE) -> NEBAUTO | K45: =VLOOKUP(A45,'Tableau single and bulk'!A:I,9,FALSE) -> 45945.388 | L45: =VLOOKUP(A45,'Tableau single and bulk'!A:L,12,FALSE) -> 609755 | M45: =VLOOKUP(A45,'Tableau single and bulk'!A:AA,27,FALSE) -> MSL Healthcare Ltd
A46: 011407M | B46: Irish Life | C46: Add Members | D46: 2025-10-10 10:53:48.643000Z | E46: 011407M | F46: Completed | G46: Active | H46: =VLOOKUP(A46,'Export Worksheet'!A:L,6,FALSE) -> #N/A | I46: =VLOOKUP(A46,'Tableau single and bulk'!A:B,2,FALSE) -> NEBAUTO | K46: =VLOOKUP(A46,'Tableau single and bulk'!A:I,9,FALSE) -> 45940.496 | L46: =VLOOKUP(A46,'Tableau single and bulk'!A:L,12,FALSE) -> 608028 | M46: =VLOOKUP(A46,'Tableau single and bulk'!A:AA,27,FALSE) -> Apple | N46: Nothing loaded
A47: 011436M | B47: Arctera International Limited | C47: Add Members | D47: 2025-10-14 09:17:23.277000Z | E47: 011436M | F47: Completed | G47: Active | H47: =VLOOKUP(A47,'Export Worksheet'!A:L,6,FALSE) -> 4 | I47: =VLOOKUP(A47,'Tableau single and bulk'!A:B,2,FALSE) -> NEBAUTO | K47: =VLOOKUP(A47,'Tableau single and bulk'!A:I,9,FALSE) -> 45944.429 | L47: =VLOOKUP(A47,'Tableau single and bulk'!A:L,12,FALSE) -> 605239 | M47: =VLOOKUP(A47,'Tableau single and bulk'!A:AA,27,FALSE) -> Arctera International Limited
A48: 011443M | B48: Irish Life | C48: Add Members | D48: 2025-10-09 11:09:26.968000Z | E48: 011443M | F48: Completed | G48: Active | H48: =VLOOKUP(A48,'Export Worksheet'!A:L,6,FALSE) -> #N/A | I48: =VLOOKUP(A48,'Tableau single and bulk'!A:B,2,FALSE) -> NEBAUTO | K48: =VLOOKUP(A48,'Tableau single and bulk'!A:I,9,FALSE) -> 45939.506 | L48: =VLOOKUP(A48,'Tableau single and bulk'!A:L,12,FALSE) -> 605064 | M48: =VLOOKUP(A48,'Tableau single and bulk'!A:AA,27,FALSE) -> Bristow Ireland Limited | N48: Batch was deleted
A49: 011470M | B49: Aon | C49: Add Members | D49: 2025-10-14 08:53:16.044000Z | E49: 011470M | F49: Completed | G49: Active | H49: =VLOOKUP(A49,'Export Worksheet'!A:L,6,FALSE) -> #N/A | I49: =VLOOKUP(A49,'Tableau single and bulk'!A:B,2,FALSE) -> NESAUTO | K49: =VLOOKUP(A49,'Tableau single and bulk'!A:I,9,FALSE) -> 45944.412 | L49: =VLOOKUP(A49,'Tableau single and bulk'!A:L,12,FALSE) -> 606951 | M49: =VLOOKUP(A49,'Tableau single and bulk'!A:AA,27,FALSE) -> Boxever Limited
A50: 011491M | B50: Aon | C50: Add Members | D50: 2025-10-14 09:55:49.876000Z | E50: 011491M | F50: Completed | G50: Active | H50: =VLOOKUP(A50,'Export Worksheet'!A:L,6,FALSE) -> #N/A | I50: =VLOOKUP(A50,'Tableau single and bulk'!A:B,2,FALSE) -> NEBAUTO | K50: =VLOOKUP(A50,'Tableau single and bulk'!A:I,9,FALSE) -> 45944.455 | L50: =VLOOKUP(A50,'Tableau single and bulk'!A:L,12,FALSE) -> 609839 | M50: =VLOOKUP(A50,'Tableau single and bulk'!A:AA,27,FALSE) -> Viatris Pension Plan | N50: errors found
A51: 011492M | B51: Irish Life | C51: Add Members | D51: 2025-10-09 11:45:40.397000Z | E51: 011492M | F51: Completed | G51: Active | H51: =VLOOKUP(A51,'Export Worksheet'!A:L,6,FALSE) -> 1 | I51: =VLOOKUP(A51,'Tableau single and bulk'!A:B,2,FALSE) -> NEBAUTO | K51: =VLOOKUP(A51,'Tableau single and bulk'!A:I,9,FALSE) -> 45939.532 | L51: =VLOOKUP(A51,'Tableau single and bulk'!A:L,12,FALSE) -> 606850 | M51: =VLOOKUP(A51,'Tableau single and bulk'!A:AA,27,FALSE) -> Tente Limited Employee Benefits Plan
A52: 011493M | B52: Unio Employee Benefits | C52: Add Members | D52: 2025-10-14 09:00:54.302000Z | E52: 011493M | F52: Completed | G52: Active | H52: =VLOOKUP(A52,'Export Worksheet'!A:L,6,FALSE) -> #N/A | I52: =VLOOKUP(A52,'Tableau single and bulk'!A:B,2,FALSE) -> NESAUTO | K52: =VLOOKUP(A52,'Tableau single and bulk'!A:I,9,FALSE) -> 45944.417 | L52: =VLOOKUP(A52,'Tableau single and bulk'!A:L,12,FALSE) -> 602656 | M52: =VLOOKUP(A52,'Tableau single and bulk'!A:AA,27,FALSE) -> Horse Sport Ireland Ltd
A53: 011510M | B53: GoTo Technologies Ireland Unlimited Co | C53: Add Members | D53: 2025-10-14 09:27:37.145000Z | E53: 011510M | F53: Completed | G53: Active | H53: =VLOOKUP(A53,'Export Worksheet'!A:L,6,FALSE) -> 2 | I53: =VLOOKUP(A53,'Tableau single and bulk'!A:B,2,FALSE) -> NEBAUTO | K53: =VLOOKUP(A53,'Tableau single and bulk'!A:I,9,FALSE) -> 45944.436 | L53: =VLOOKUP(A53,'Tableau single and bulk'!A:L,12,FALSE) -> 603754 | M53: =VLOOKUP(A53,'Tableau single and bulk'!A:AA,27,FALSE) -> GoTo Technologies Ireland Unlimited Co.
A54: 011531M | B54: Tokyo Electron Europe Ltd | C54: Add Members | D54: 2025-10-11 09:36:13.763000Z | E54: 011531M | F54: Completed | G54: Active | H54: =VLOOKUP(A54,'Export Worksheet'!A:L,6,FALSE) -> #N/A | I54: =VLOOKUP(A54,'Tableau single and bulk'!A:B,2,FALSE) -> NESAUTO | K54: =VLOOKUP(A54,'Tableau single and bulk'!A:I,9,FALSE) -> 45941.442 | L54: =VLOOKUP(A54,'Tableau single and bulk'!A:L,12,FALSE) -> 601397 | M54: =VLOOKUP(A54,'Tableau single and bulk'!A:AA,27,FALSE) -> Tokyo Electron Europe Ltd
A55: 011534M | B55: Irish Life | C55: Add Members | D55: 2025-10-13 14:42:51.439000Z | E55: 011534M | F55: Completed | G55: Active | H55: =VLOOKUP(A55,'Export Worksheet'!A:L,6,FALSE) -> 1 | I55: =VLOOKUP(A55,'Tableau single and bulk'!A:B,2,FALSE) -> NEBAUTO | K55: =VLOOKUP(A55,'Tableau single and bulk'!A:I,9,FALSE) -> 45943.655 | L55: =VLOOKUP(A55,'Tableau single and bulk'!A:L,12,FALSE) -> 603768 | M55: =VLOOKUP(A55,'Tableau single and bulk'!A:AA,27,FALSE) -> Natures Best Limited
A56: 011536M | B56: Tokyo Electron Europe Ltd | C56: Add Members | D56: 2025-10-11 09:33:17.969000Z | E56: 011536M | F56: Completed | G56: Active | H56: =VLOOKUP(A56,'Export Worksheet'!A:L,6,FALSE) -> #N/A | I56: =VLOOKUP(A56,'Tableau single and bulk'!A:B,2,FALSE) -> NESAUTO | K56: =VLOOKUP(A56,'Tableau single and bulk'!A:I,9,FALSE) -> 45941.44 | L56: =VLOOKUP(A56,'Tableau single and bulk'!A:L,12,FALSE) -> 601397 | M56: =VLOOKUP(A56,'Tableau single and bulk'!A:AA,27,FALSE) -> Tokyo Electron Europe Ltd
A57: 011560M | B57: Irish Life | C57: Add Members | D57: 2025-10-09 15:04:15.052000Z | E57: 011560M | F57: Completed | G57: Active | H57: =VLOOKUP(A57,'Export Worksheet'!A:L,6,FALSE) -> 61 | I57: =VLOOKUP(A57,'Tableau single and bulk'!A:B,2,FALSE) -> NEBAUTO | K57: =VLOOKUP(A57,'Tableau single and bulk'!A:I,9,FALSE) -> 45939.67 | L57: =VLOOKUP(A57,'Tableau single and bulk'!A:L,12,FALSE) -> 606821 | M57: =VLOOKUP(A57,'Tableau single and bulk'!A:AA,27,FALSE) -> Siemens Energy Ireland Limited
A58: 011575M | B58: Irish Life | C58: Add Members | D58: 2025-10-14 13:10:53.107000Z | E58: 011575M | F58: Completed | G58: Active | H58: =VLOOKUP(A58,'Export Worksheet'!A:L,6,FALSE) -> 18 | I58: =VLOOKUP(A58,'Tableau single and bulk'!A:B,2,FALSE) -> NEBAUTO | K58: =VLOOKUP(A58,'Tableau single and bulk'!A:I,9,FALSE) -> 45944.591 | L58: =VLOOKUP(A58,'Tableau single and bulk'!A:L,12,FALSE) -> 608028 | M58: =VLOOKUP(A58,'Tableau single and bulk'!A:AA,27,FALSE) -> Apple
A59: 011580M | B59: Irish Life | C59: Add Members | D59: 2025-10-14 13:52:53.350000Z | E59: 011580M | F59: Completed | G59: Active | H59: =VLOOKUP(A59,'Export Worksheet'!A:L,6,FALSE) -> 2 | I59: =VLOOKUP(A59,'Tableau single and bulk'!A:B,2,FALSE) -> NEBAUTO | K59: =VLOOKUP(A59,'Tableau single and bulk'!A:I,9,FALSE) -> 45944.62 | L59: =VLOOKUP(A59,'Tableau single and bulk'!A:L,12,FALSE) -> 603525 | M59: =VLOOKUP(A59,'Tableau single and bulk'!A:AA,27,FALSE) -> National Advocacy Service
A60: 011597M | B60: Toasttab Ireland Limited | C60: Add Members | D60: 2025-10-14 12:53:37.374000Z | E60: 011597M | F60: Completed | G60: Active | H60: =VLOOKUP(A60,'Export Worksheet'!A:L,6,FALSE) -> 7 | I60: =VLOOKUP(A60,'Tableau single and bulk'!A:B,2,FALSE) -> NEBAUTO | K60: =VLOOKUP(A60,'Tableau single and bulk'!A:I,9,FALSE) -> 45944.579 | L60: =VLOOKUP(A60,'Tableau single and bulk'!A:L,12,FALSE) -> 603965 | M60: =VLOOKUP(A60,'Tableau single and bulk'!A:AA,27,FALSE) -> Toasttab Ireland Limited
A61: 011615M | B61: BearingPoint Ireland Limited | C61: Add Members | D61: 2025-10-14 13:28:08.440000Z | E61: 011615M | F61: Completed | G61: Active | H61: =VLOOKUP(A61,'Export Worksheet'!A:L,6,FALSE) -> 40 | I61: =VLOOKUP(A61,'Tableau single and bulk'!A:B,2,FALSE) -> NEBAUTO | K61: =VLOOKUP(A61,'Tableau single and bulk'!A:I,9,FALSE) -> 45944.603 | L61: =VLOOKUP(A61,'Tableau single and bulk'!A:L,12,FALSE) -> 609970 | M61: =VLOOKUP(A61,'Tableau single and bulk'!A:AA,27,FALSE) -> BearingPoint Ireland Limited
A62: 011617M | B62: Blackrock Health | C62: Add Members | D62: 2025-10-14 09:40:45.169000Z | E62: 011617M | F62: Completed | G62: Active | H62: =VLOOKUP(A62,'Export Worksheet'!A:L,6,FALSE) -> #N/A | I62: =VLOOKUP(A62,'Tableau single and bulk'!A:B,2,FALSE) -> NESAUTO | K62: =VLOOKUP(A62,'Tableau single and bulk'!A:I,9,FALSE) -> 45944.445 | L62: =VLOOKUP(A62,'Tableau single and bulk'!A:L,12,FALSE) -> 609841 | M62: =VLOOKUP(A62,'Tableau single and bulk'!A:AA,27,FALSE) -> Galway Clinic Doughiska Unltd Co
A63: 011619M | B63: WTW | C63: Add Members | D63: 2025-10-10 15:19:39.423000Z | E63: 011619M | F63: Completed | G63: Active | H63: =VLOOKUP(A63,'Export Worksheet'!A:L,6,FALSE) -> #N/A | I63: =VLOOKUP(A63,'Tableau single and bulk'!A:B,2,FALSE) -> NEBAUTO | K63: =VLOOKUP(A63,'Tableau single and bulk'!A:I,9,FALSE) -> 45940.68 | L63: =VLOOKUP(A63,'Tableau single and bulk'!A:L,12,FALSE) -> 603691 | M63: =VLOOKUP(A63,'Tableau single and bulk'!A:AA,27,FALSE) -> Palo Alto Security Limited | N63: errors found | O63: Just closed and created another bulk
A64: 011621M | B64: Patrick J Tobin Ltd | C64: Add Members | D64: 2025-10-15 09:34:45.943000Z | E64: 011621M | F64: Completed | G64: Active | H64: =VLOOKUP(A64,'Export Worksheet'!A:L,6,FALSE) -> 1 | I64: =VLOOKUP(A64,'Tableau single and bulk'!A:B,2,FALSE) -> NEBAUTO | K64: =VLOOKUP(A64,'Tableau single and bulk'!A:I,9,FALSE) -> 45945.441 | L64: =VLOOKUP(A64,'Tableau single and bulk'!A:L,12,FALSE) -> 602944 | M64: =VLOOKUP(A64,'Tableau single and bulk'!A:AA,27,FALSE) -> PATRICK J TOBIN LTD
A65: 011645M | B65: Moneywise Financial Planning Ltd | C65: Add Members | D65: 2025-10-14 12:59:55.282000Z | E65: 011645M | F65: Completed | G65: Active | H65: =VLOOKUP(A65,'Export Worksheet'!A:L,6,FALSE) -> #N/A | I65: =VLOOKUP(A65,'Tableau single and bulk'!A:B,2,FALSE) -> NESAUTO | K65: =VLOOKUP(A65,'Tableau single and bulk'!A:I,9,FALSE) -> 45944.583 | L65: =VLOOKUP(A65,'Tableau single and bulk'!A:L,12,FALSE) -> 601479 | M65: =VLOOKUP(A65,'Tableau single and bulk'!A:AA,27,FALSE) -> ByrneWallace RS Plan
A66: 011683M | B66: IHI Group | C66: Add Members | D66: 2025-10-14 09:15:06.134000Z | E66: 011683M | F66: Completed | G66: Active | H66: =VLOOKUP(A66,'Export Worksheet'!A:L,6,FALSE) -> #N/A | I66: =VLOOKUP(A66,'Tableau single and bulk'!A:B,2,FALSE) -> NESAUTO | K66: =VLOOKUP(A66,'Tableau single and bulk'!A:I,9,FALSE) -> 45944.427 | L66: =VLOOKUP(A66,'Tableau single and bulk'!A:L,12,FALSE) -> 603833 | M66: =VLOOKUP(A66,'Tableau single and bulk'!A:AA,27,FALSE) -> Keeper Security EMEA Limited
A67: 011697M | B67: Killarney Hotels Limited | C67: Add Members | D67: 2025-10-15 08:17:57.992000Z | E67: 011697M | F67: Completed | G67: Active | H67: =VLOOKUP(A67,'Export Worksheet'!A:L,6,FALSE) -> 1 | I67: =VLOOKUP(A67,'Tableau single and bulk'!A:B,2,FALSE) -> NEBAUTO | K67: =VLOOKUP(A67,'Tableau single and bulk'!A:I,9,FALSE) -> 45945.387 | L67: =VLOOKUP(A67,'Tableau single and bulk'!A:L,12,FALSE) -> 606901 | M67: =VLOOKUP(A67,'Tableau single and bulk'!A:AA,27,FALSE) -> Killarney Hotels Limited
A68: 011702M | B68: Ethos Engineering Limited | C68: Add Members | D68: 2025-10-14 15:33:11.389000Z | E68: 011702M | F68: Completed | G68: Active | H68: =VLOOKUP(A68,'Export Worksheet'!A:L,6,FALSE) -> #N/A | I68: =VLOOKUP(A68,'Tableau single and bulk'!A:B,2,FALSE) -> NESAUTO | K68: =VLOOKUP(A68,'Tableau single and bulk'!A:I,9,FALSE) -> 45944.69 | L68: =VLOOKUP(A68,'Tableau single and bulk'!A:L,12,FALSE) -> 603165 | M68: =VLOOKUP(A68,'Tableau single and bulk'!A:AA,27,FALSE) -> Ethos Engineering Limited
A69: 011703M | B69: East Cork Oil Company | C69: Add Members | D69: 2025-10-14 12:25:57.602000Z | E69: 011703M | F69: Completed | G69: Active | H69: =VLOOKUP(A69,'Export Worksheet'!A:L,6,FALSE) -> 13 | I69: =VLOOKUP(A69,'Tableau single and bulk'!A:B,2,FALSE) -> NEBAUTO | K69: =VLOOKUP(A69,'Tableau single and bulk'!A:I,9,FALSE) -> 45944.56 | L69: =VLOOKUP(A69,'Tableau single and bulk'!A:L,12,FALSE) -> 602254 | M69: =VLOOKUP(A69,'Tableau single and bulk'!A:AA,27,FALSE) -> East Cork Oil Company Unlimited Company
A70: 011722M | B70: Opening HR Limited | C70: Add Members | D70: 2025-10-14 13:36:52.337000Z | E70: 011722M | F70: Completed | G70: Active | H70: =VLOOKUP(A70,'Export Worksheet'!A:L,6,FALSE) -> 1 | I70: =VLOOKUP(A70,'Tableau single and bulk'!A:B,2,FALSE) -> NEBAUTO | K70: =VLOOKUP(A70,'Tableau single and bulk'!A:I,9,FALSE) -> 45944.609 | L70: =VLOOKUP(A70,'Tableau single and bulk'!A:L,12,FALSE) -> 606859 | M70: =VLOOKUP(A70,'Tableau single and bulk'!A:AA,27,FALSE) -> Opening HR Limited
A71: 011902M | B71: Smartply Europe Limited | C71: Add Members | D71: 2025-10-10 10:30:34.770000Z | E71: 011902M | F71: Completed | G71: Active | H71: =VLOOKUP(A71,'Export Worksheet'!A:L,6,FALSE) -> #N/A | I71: =VLOOKUP(A71,'Tableau single and bulk'!A:B,2,FALSE) -> NEBAUTO | K71: =VLOOKUP(A71,'Tableau single and bulk'!A:I,9,FALSE) -> 45940.48 | L71: =VLOOKUP(A71,'Tableau single and bulk'!A:L,12,FALSE) -> 603658 | M71: =VLOOKUP(A71,'Tableau single and bulk'!A:AA,27,FALSE) -> Smartply Europe DAC
A72: 011920M | B72: Waterford Intellectual Disability Association CLG | C72: Add Members | D72: 2025-10-14 08:14:52.395000Z | E72: 011920M | F72: Completed | G72: Active | H72: =VLOOKUP(A72,'Export Worksheet'!A:L,6,FALSE) -> 1 | I72: =VLOOKUP(A72,'Tableau single and bulk'!A:B,2,FALSE) -> NEBAUTO | K72: =VLOOKUP(A72,'Tableau single and bulk'!A:I,9,FALSE) -> 45944.385 | L72: =VLOOKUP(A72,'Tableau single and bulk'!A:L,12,FALSE) -> 609707 | M72: =VLOOKUP(A72,'Tableau single and bulk'!A:AA,27,FALSE) -> NFVSP Waterford Intellectual Disability
A73: 011928M | B73: St Vincents Healthcare Group | C73: Add Members | D73: 2025-10-15 10:46:13.366000Z | E73: 011928M | F73: Completed | G73: Active | H73: =VLOOKUP(A73,'Export Worksheet'!A:L,6,FALSE) -> 31 | I73: =VLOOKUP(A73,'Tableau single and bulk'!A:B,2,FALSE) -> NEBAUTO | K73: =VLOOKUP(A73,'Tableau single and bulk'!A:I,9,FALSE) -> 45945.49 | L73: =VLOOKUP(A73,'Tableau single and bulk'!A:L,12,FALSE) -> 602166 | M73: =VLOOKUP(A73,'Tableau single and bulk'!A:AA,27,FALSE) -> St Vincent's Private Hospital
A74: 011946M | B74: MeiraGTx Ireland DAC | C74: Add Members | D74: 2025-10-15 09:28:24.671000Z | E74: 011946M | F74: Completed | G74: Active | H74: =VLOOKUP(A74,'Export Worksheet'!A:L,6,FALSE) -> 4 | I74: =VLOOKUP(A74,'Tableau single and bulk'!A:B,2,FALSE) -> NEBAUTO | K74: =VLOOKUP(A74,'Tableau single and bulk'!A:I,9,FALSE) -> 45945.436 | L74: =VLOOKUP(A74,'Tableau single and bulk'!A:L,12,FALSE) -> 606866 | M74: =VLOOKUP(A74,'Tableau single and bulk'!A:AA,27,FALSE) -> MeiraGTX Ireland DAC
A75: 011956M | B75: Irish Life | C75: Add Members | D75: 2025-10-10 11:38:13.742000Z | E75: 011956M | F75: Completed | G75: Active | H75: =VLOOKUP(A75,'Export Worksheet'!A:L,6,FALSE) -> 3 | I75: =VLOOKUP(A75,'Tableau single and bulk'!A:B,2,FALSE) -> NEBAUTO | K75: =VLOOKUP(A75,'Tableau single and bulk'!A:I,9,FALSE) -> 45940.526 | L75: =VLOOKUP(A75,'Tableau single and bulk'!A:L,12,FALSE) -> 609914 | M75: =VLOOKUP(A75,'Tableau single and bulk'!A:AA,27,FALSE) -> Agri Health DC Pension Scheme
A76: 011958M | B76: Ornua Co Operative Limited | C76: Add Members | D76: 2025-10-15 12:18:47.551000Z | E76: 011958M | F76: Completed | G76: Active | H76: =VLOOKUP(A76,'Export Worksheet'!A:L,6,FALSE) -> 27 | I76: =VLOOKUP(A76,'Tableau single and bulk'!A:B,2,FALSE) -> NEBAUTO | K76: =VLOOKUP(A76,'Tableau single and bulk'!A:I,9,FALSE) -> 45945.554 | L76: =VLOOKUP(A76,'Tableau single and bulk'!A:L,12,FALSE) -> 602833 | M76: =VLOOKUP(A76,'Tableau single and bulk'!A:AA,27,FALSE) -> Ornua Co-Operative Limited
A77: 011966M | B77: Thermo Fisher Scientific | C77: Add Members | D77: 2025-10-14 07:28:10.093000Z | E77: 011966M | F77: Completed | G77: Active | H77: =VLOOKUP(A77,'Export Worksheet'!A:L,6,FALSE) -> #N/A | I77: =VLOOKUP(A77,'Tableau single and bulk'!A:B,2,FALSE) -> NEBAUTO | K77: =VLOOKUP(A77,'Tableau single and bulk'!A:I,9,FALSE) -> 45944.353 | L77: =VLOOKUP(A77,'Tableau single and bulk'!A:L,12,FALSE) -> 601299 | M77: =VLOOKUP(A77,'Tableau single and bulk'!A:AA,27,FALSE) -> Thermo Fisher Scientific Cork Limited | N77: Nothing loaded
A78: 011972M | B78: Magnet Networks Ltd | C78: Add Members | D78: 2025-10-15 09:38:57.666000Z | E78: 011972M | F78: Completed | G78: Active | H78: =VLOOKUP(A78,'Export Worksheet'!A:L,6,FALSE) -> 1 | I78: =VLOOKUP(A78,'Tableau single and bulk'!A:B,2,FALSE) -> NEBAUTO | K78: =VLOOKUP(A78,'Tableau single and bulk'!A:I,9,FALSE) -> 45945.444 | L78: =VLOOKUP(A78,'Tableau single and bulk'!A:L,12,FALSE) -> 603409 | M78: =VLOOKUP(A78,'Tableau single and bulk'!A:AA,27,FALSE) -> Magnet Networks Limited
A79: 011982M | B79: Ingersoll Rand Industrial Ire Limited | C79: Add Members | D79: 2025-10-14 13:17:46.846000Z | E79: 011982M | F79: Completed | G79: Active | H79: =VLOOKUP(A79,'Export Worksheet'!A:L,6,FALSE) -> #N/A | I79: =VLOOKUP(A79,'Tableau single and bulk'!A:B,2,FALSE) -> NESAUTO | K79: =VLOOKUP(A79,'Tableau single and bulk'!A:I,9,FALSE) -> 45944.596 | L79: =VLOOKUP(A79,'Tableau single and bulk'!A:L,12,FALSE) -> 606872 | M79: =VLOOKUP(A79,'Tableau single and bulk'!A:AA,27,FALSE) -> Ingersoll- Rand Industrial Ire. Limited
A80: 011988M | B80: Booking Holdings Financial Services Intl Ltd | C80: Add Members | D80: 2025-10-15 14:36:56.664000Z | E80: 011988M | F80: Completed | G80: Active | H80: =VLOOKUP(A80,'Export Worksheet'!A:L,6,FALSE) -> 7 | I80: =VLOOKUP(A80,'Tableau single and bulk'!A:B,2,FALSE) -> NEBAUTO | K80: =VLOOKUP(A80,'Tableau single and bulk'!A:I,9,FALSE) -> 45945.651 | L80: =VLOOKUP(A80,'Tableau single and bulk'!A:L,12,FALSE) -> 606840 | M80: =VLOOKUP(A80,'Tableau single and bulk'!A:AA,27,FALSE) -> Booking Holdings Fin. Serv. Intl Ltd
A81: 011991M | B81: St Christophers Services CLG | C81: Add Members | D81: 2025-10-14 08:25:03.892000Z | E81: 011991M | F81: Completed | G81: Active | H81: =VLOOKUP(A81,'Export Worksheet'!A:L,6,FALSE) -> 1 | I81: =VLOOKUP(A81,'Tableau single and bulk'!A:B,2,FALSE) -> NEBAUTO | K81: =VLOOKUP(A81,'Tableau single and bulk'!A:I,9,FALSE) -> 45944.392 | L81: =VLOOKUP(A81,'Tableau single and bulk'!A:L,12,FALSE) -> 609702 | M81: =VLOOKUP(A81,'Tableau single and bulk'!A:AA,27,FALSE) -> NFVSP St Christopher's Services CLG
A82: 011994M | B82: Blackrock Health | C82: Add Members | D82: 2025-10-15 09:51:25.622000Z | E82: 011994M | F82: Completed | G82: Active | H82: =VLOOKUP(A82,'Export Worksheet'!A:L,6,FALSE) -> #N/A | I82: =VLOOKUP(A82,'Tableau single and bulk'!A:B,2,FALSE) -> NESAUTO | K82: =VLOOKUP(A82,'Tableau single and bulk'!A:I,9,FALSE) -> 45945.452 | L82: =VLOOKUP(A82,'Tableau single and bulk'!A:L,12,FALSE) -> 609841 | M82: =VLOOKUP(A82,'Tableau single and bulk'!A:AA,27,FALSE) -> Galway Clinic Doughiska Unltd Co
A83: 011999M | B83: Magnet Networks Ltd | C83: Add Members | D83: 2025-10-15 09:23:11.048000Z | E83: 011999M | F83: Completed | G83: Active | H83: =VLOOKUP(A83,'Export Worksheet'!A:L,6,FALSE) -> 1 | I83: =VLOOKUP(A83,'Tableau single and bulk'!A:B,2,FALSE) -> NEBAUTO | K83: =VLOOKUP(A83,'Tableau single and bulk'!A:I,9,FALSE) -> 45945.433 | L83: =VLOOKUP(A83,'Tableau single and bulk'!A:L,12,FALSE) -> 609819 | M83: =VLOOKUP(A83,'Tableau single and bulk'!A:AA,27,FALSE) -> Enet Defined Contribution Plan
A84: 012015M | B84: Hertz Europe Service Centre Limited | C84: Add Members | D84: 2025-10-15 08:49:19.111000Z | E84: 012015M | F84: Completed | G84: Active | H84: =VLOOKUP(A84,'Export Worksheet'!A:L,6,FALSE) -> 8 | I84: =VLOOKUP(A84,'Tableau single and bulk'!A:B,2,FALSE) -> NEBAUTO | K84: =VLOOKUP(A84,'Tableau single and bulk'!A:I,9,FALSE) -> 45945.409 | L84: =VLOOKUP(A84,'Tableau single and bulk'!A:L,12,FALSE) -> 609621 | M84: =VLOOKUP(A84,'Tableau single and bulk'!A:AA,27,FALSE) -> Hertz Europe Service Centre Limited
A85: 012020M | B85: Stryker Ireland | C85: Add Members | D85: 2025-10-15 13:05:46.704000Z | E85: 012020M | F85: Completed | G85: Active | H85: =VLOOKUP(A85,'Export Worksheet'!A:L,6,FALSE) -> 2 | I85: =VLOOKUP(A85,'Tableau single and bulk'!A:B,2,FALSE) -> NEBAUTO | K85: =VLOOKUP(A85,'Tableau single and bulk'!A:I,9,FALSE) -> 45945.587 | L85: =VLOOKUP(A85,'Tableau single and bulk'!A:L,12,FALSE) -> 603990 | M85: =VLOOKUP(A85,'Tableau single and bulk'!A:AA,27,FALSE) -> Stryker Ireland DC Pension Plan
A86: 012033M | B86: Royal London | C86: Add Members | D86: 2025-10-13 10:39:17.217000Z | E86: 012033M | F86: Completed | G86: Active | H86: =VLOOKUP(A86,'Export Worksheet'!A:L,6,FALSE) -> 3 | I86: =VLOOKUP(A86,'Tableau single and bulk'!A:B,2,FALSE) -> NEBAUTO | K86: =VLOOKUP(A86,'Tableau single and bulk'!A:I,9,FALSE) -> 45943.486 | L86: =VLOOKUP(A86,'Tableau single and bulk'!A:L,12,FALSE) -> 603549 | M86: =VLOOKUP(A86,'Tableau single and bulk'!A:AA,27,FALSE) -> Royal London Mutual Ins. Society Ltd.
A87: 012035M | B87: Unio Employee Benefits | C87: Add Members | D87: 2025-10-15 15:29:21.230000Z | E87: 012035M | F87: Completed | G87: Active | H87: =VLOOKUP(A87,'Export Worksheet'!A:L,6,FALSE) -> 1 | I87: =VLOOKUP(A87,'Tableau single and bulk'!A:B,2,FALSE) -> NEBAUTO | K87: =VLOOKUP(A87,'Tableau single and bulk'!A:I,9,FALSE) -> 45945.687 | L87: =VLOOKUP(A87,'Tableau single and bulk'!A:L,12,FALSE) -> 602238 | M87: =VLOOKUP(A87,'Tableau single and bulk'!A:AA,27,FALSE) -> ActiveCampaign Ireland Limited
A88: 012047M | B88: Society of Saint Vincent De Paul | C88: Add Members | D88: 2025-10-15 09:46:33.757000Z | E88: 012047M | F88: Completed | G88: Active | H88: =VLOOKUP(A88,'Export Worksheet'!A:L,6,FALSE) -> #N/A | I88: =VLOOKUP(A88,'Tableau single and bulk'!A:B,2,FALSE) -> NESAUTO | K88: =VLOOKUP(A88,'Tableau single and bulk'!A:I,9,FALSE) -> 45945.449 | L88: =VLOOKUP(A88,'Tableau single and bulk'!A:L,12,FALSE) -> 602631 | M88: =VLOOKUP(A88,'Tableau single and bulk'!A:AA,27,FALSE) -> Society of Saint Vincent De Paul
A89: 012060M | B89: Fold Housing Association Company IRL Ltd | C89: Add Members | D89: 2025-10-13 14:01:13.469000Z | E89: 012060M | F89: Completed | G89: Active | H89: =VLOOKUP(A89,'Export Worksheet'!A:L,6,FALSE) -> #N/A | I89: =VLOOKUP(A89,'Tableau single and bulk'!A:B,2,FALSE) -> NESAUTO | K89: =VLOOKUP(A89,'Tableau single and bulk'!A:I,9,FALSE) -> 45943.626 | L89: =VLOOKUP(A89,'Tableau single and bulk'!A:L,12,FALSE) -> 603473 | M89: =VLOOKUP(A89,'Tableau single and bulk'!A:AA,27,FALSE) -> Fold Housing Association Ireland Ltd.
... A527: 997990L | B527: Mincon International Limited | C527: Add Members | D527: 2025-10-09 20:53:57.283000Z | E527: 997990L | F527: Completed | G527: Active | H527: =VLOOKUP(A527,'Export Worksheet'!A:L,6,FALSE) -> #N/A | I527: =VLOOKUP(A527,'Tableau single and bulk'!A:B,2,FALSE) -> NESAUTO | K527: =VLOOKUP(A527,'Tableau single and bulk'!A:I,9,FALSE) -> 45939.912 | L527: =VLOOKUP(A527,'Tableau single and bulk'!A:L,12,FALSE) -> 601385 | M527: =VLOOKUP(A527,'Tableau single and bulk'!A:AA,27,FALSE) -> Mincon International Limited

Sheet Tableau single and bulk
A1: Midas Number | B1: Worktype | C1: Service Calculation | D1: Service Summary | E1: Allocated User | F1: Broker Code | G1: Completed By ID | H1: Completed date range | I1: Date Completed | J1: DC Teams | K1: Member Number | L1: Scheme Number | M1: Select Context | N1: TP2V3_WI_EFFORT | O1: TP2V3_WI_ORIGINATOR | P1: TP2V3_WI_SOURCE | Q1: Worktype Description | R1: Worktype TYPE | S1: Allocated Team | T1: Context | U1: Date Created | V1: Process Deadline | W1: Number of Records | X1: Turnaround Time | Y1: Broker Name | Z1: Object_ID | AA1: Scheme Name | AB1: Status | AC1: TP2V3_DESCRIPTION | AD1: TP2V3_SOURCE_INTEXT | AE1: TP2V3_WI_BREAKDOWN_TOTAL | AF1: TP2V3_WI_EFFORT_QC | AG1: TP2V3_WI_PEND_REASON | AH1: TP2V3_WI_QC_CHECKER | AI1: TP2V3_WI_QC_COMP_DATE | AJ1: TP2V3_WI_QC_COMPLETE | AK1: TP2V3_WI_QC_RESULT | AL1: TP2V3_WI_QC_RESULT_INIT | AM1: TP2V3_WI_QC_ROOT_CAUSE | AN1: TP2V3_WI_QC_USER | AO1: TP2V3_WI_TEAM_CODE | AP1: WI_CLI_INDICATOR
A2: 010921M | B2: NESAUTO | C2: Day 4 | D2: In Service | E2: Y337 | F2: A300 | G2: Y337 | H2: TRUE | I2: 45943.593 | J2: Auto Enrolment DC | K2: 1201945 | L2: 603757 | M2: DC | P2: SecureShare eircom | Q2: DC | R2: 1 | S2: Auto Enrolment DC | T2: DC | U2: 45938.468 | V2: 45943.958 | W2: 1 | X2: 3.124919 | Y2: ILFS Corporate Business | Z2: 25281CBPR02EF52 | AA2: eircom Limited AVC Scheme | AB2: Completed | AC2: John Fitzgerald - added 1201945 | AD2: INTERNAL | AE2: 1 | AO2: TM32 | AP2: N
A3: 010928M | B3: NEBAUTO | C3: Day 4 | D3: In Service | E3: C192 | F3: S168 | G3: C192 | H3: TRUE | I3: 45943.643 | J3: Auto Enrolment DC | L3: 603026 | M3: DC | P3: SecureShare Vestas I | Q3: DC | R3: 1 | S3: Auto Enrolment DC | T3: DC | U3: 45938.474 | V3: 45943.958 | W3: 1 | X3: 3.1693171 | Y3: Mercer (Elect Existing Business) | Z3: 25281CBPR02EFE2 | AA3: Vestas Ireland Limited | AB3: Completed | AC3: Employer: Vestas Ireland LTD :: Number of Members: 1 | AD3: INTERNAL | AE3: 1 | AO3: TM30 | AP3: N
A4: 010931M | B4: NEBAUTO | C4: Day 4 | D4: In Service | E4: Y337 | F4: A300 | G4: Y337 | H4: TRUE | I4: 45943.514 | J4: Auto Enrolment DC | L4: 605376 | M4: DC | P4: SecureShare Kerry Gr | Q4: DC | R4: 1 | S4: Auto Enrolment DC | T4: DC | U4: 45938.477 | V4: 45943.958 | W4: 1 | X4: 3.0367477 | Y4: ILFS Corporate Business | Z4: 25281CBPR02F032 | AA4: Kerry Dairy Holdings (Ireland) Limited | AB4: Completed | AC4: 27 NEs N/A :: Number of Members: N/A | AD4: INTERNAL | AE4: 1 | AO4: TM32 | AP4: N
A5: 010937M | B5: NESAUTO | C5: Day 5 + | D5: In Service | E5: F243 | F5: RT02 | G5: F243 | H5: TRUE | I5: 45949.586 | J5: Auto Enrolment DC | K5: 4005562 | L5: 602631 | M5: DC | P5: SecureShare Society | Q5: DC | R5: 1 | S5: Auto Enrolment DC | T5: DC | U5: 45938.479 | V5: 45950.958 | W5: 1 | X5: 7.1076157 | Y5: PWC Financial Consulting DAC | Z5: 25281CBPR02F082 | AA5: Society of Saint Vincent De Paul | AB5: Completed | AC5: Employer: Society of Saint Vincent de Paul :: ... (see attached file for full description) | AD5: INTERNAL | AE5: 1 | AO5: TM33 | AP5: N
A6: 010991M | B6: NEBAUTO | C6: Day 3 | D6: In Service | E6: X967 | F6: TU84 | G6: x967 | H6: TRUE | I6: 45940.656 | J6: Auto Enrolment DC | L6: 609763 | M6: DC | P6: SecureShare Joseph G | Q6: DC | R6: 1 | S6: Auto Enrolment DC | T6: DC | U6: 45938.531 | V6: 45943.958 | W6: 1 | X6: 2.1247801 | Y6: Joseph G. Byrne & Sons Consulting | Z6: 25281CBPR02F4B7 | AA6: Belvedere College SJ | AB6: Completed | AC6: Molly O'Hare | AD6: INTERNAL | AE6: 1 | AO6: TM07 | AP6: N
A7: 010996M | B7: NEBAUTO | C7: Day 4 | D7: In Service | E7: Y337 | F7: A300 | G7: Y337 | H7: TRUE | I7: 45943.631 | J7: Auto Enrolment DC | L7: 603990 | M7: DC | P7: SecureShare Stryker | Q7: DC | R7: 1 | S7: Auto Enrolment DC | T7: DC | U7: 45938.532 | V7: 45943.958 | W7: 1 | X7: 3.0985532 | Y7: ILFS Corporate Business | Z7: 25281CBPR02F4B8 | AA7: Stryker Ireland DC Pension Plan | AB7: Completed | AC7: 66 NEs N/A :: Number of Members: N/A | AD7: INTERNAL | AE7: 1 | AO7: TM32 | AP7: N
A8: 010998M | B8: NEBAUTO | C8: Day 3 | D8: In Service | E8: Y337 | F8: A300 | G8: Y337 | H8: TRUE | I8: 45943.496 | J8: Auto Enrolment DC | L8: 602167 | M8: DC | P8: SecureShare Stryker | Q8: DC | R8: 1 | S8: Auto Enrolment DC | T8: DC | U8: 45938.533 | V8: 45943.958 | W8: 1 | X8: 2.9623611 | Y8: ILFS Corporate Business | Z8: 25281CBPR02F4ED | AA8: Stryker Ireland Limited Pension Scheme | AB8: Completed | AC8: 2 NEs N/A :: Number of Members: N/A | AD8: INTERNAL | AE8: 1 | AO8: TM32 | AP8: N
A9: 011003M | B9: NESAUTO | C9: Day 2 | D9: In Service | E9: J987 | F9: NK89 | G9: J987 | H9: TRUE | I9: 45939.87 | J9: Auto Enrolment DC | K9: 1201450 | L9: 609838 | M9: DC | P9: SecureShare PHX Irel | Q9: DC | R9: 1 | S9: Auto Enrolment DC | T9: DC | U9: 45938.536 | V9: 45943.958 | W9: 1 | X9: 1.3339815 | Y9: Aon Ireland Ltd. | Z9: 25281CBPR02F506 | AA9: PHX Ireland Group Limited | AB9: Completed | AC9: Employer: TCP Homecare :: Member Name: Rebekah Duffy :: Date of Birth: 12/09/1992 | AD9: INTERNAL | AE9: 1 | AO9: TM02 | AP9: N
A10: 011007M | B10: NEBAUTO | C10: Day 3 | D10: In Service | E10: Y337 | F10: A300 | G10: Y337 | H10: TRUE | I10: 45943.537 | J10: Auto Enrolment DC | L10: 603888 | M10: DC | P10: SecureShare Kerry Gr | Q10: DC | R10: 1 | S10: Auto Enrolment DC | T10: DC | U10: 45938.542 | V10: 45943.958 | W10: 1 | X10: 2.9952315 | Y10: ILFS Corporate Business | Z10: 25281CBPR02F551 | AA10: Kerry Group Plc | AB10: Completed | AC10: 50 NEs - Kerry Group Services Ltd :: Number of Members: N/A | AD10: INTERNAL | AE10: 1 | AO10: TM32 | AP10: N
A11: 011018M | B11: NESAUTO | C11: Day 3 | D11: In Service | E11: x967 | F11: A612 | G11: x967 | H11: TRUE | I11: 45940.728 | J11: Auto Enrolment DC | K11: 1201694 | L11: 609805 | M11: DC | P11: SecureShare Aon | Q11: DC | R11: 1 | S11: Auto Enrolment DC | T11: DC | U11: 45938.563 | V11: 45943.958 | W11: 1 | X11: 2.1651736 | Y11: Aon Ireland Ltd. | Z11: 25281CBPR02F644 | AA11: Aztec Financial Services (Irl) Limited | AB11: Completed | AC11: Employer: Aztec :: Member Name: Ms Rosie Allemby :: Date of Birth: 08/07/1997 | AD11: INTERNAL | AE11: 1 | AO11: TM01 | AP11: N
A12: 011019M | B12: NESAUTO | C12: Day 3 | D12: In Service | E12: x967 | F12: A612 | G12: x967 | H12: TRUE | I12: 45943.413 | J12: Auto Enrolment DC | K12: 1201746 | L12: 609805 | M12: DC | P12: SecureShare Aon | Q12: DC | R12: 1 | S12: Auto Enrolment DC | T12: DC | U12: 45938.563 | V12: 45943.958 | W12: 1 | X12: 2.8497222 | Y12: Aon Ireland Ltd. | Z12: 25281CBPR02F645 | AA12: Aztec Financial Services (Irl) Limited | AB12: Completed | AC12: Employer: Aztec :: Member Name: Miss Nivethitha Dharmaraja :: Date of Birth: 10/03/1998 | AD12: INTERNAL | AE12: 1 | AO12: TM01 | AP12: N
A13: 011021M | B13: NESAUTO | C13: Day 3 | D13: In Service | E13: S143 | F13: NJ23 | G13: S143 | H13: TRUE | I13: 45943.501 | J13: Auto Enrolment DC | K13: 1201851 | L13: 603261 | M13: DC | P13: SecureShare Unio Emp | Q13: DC | R13: 1 | S13: Auto Enrolment DC | T13: DC | U13: 45938.567 | V13: 45943.958 | W13: 1 | X13: 2.9339352 | Y13: Unio Ltd | Z13: 25281CBPR02F669 | AA13: Euler Hermes Services Ireland Ltd | AB13: Completed | AC13: Sowmiya Dhamodhara 1201851 | AD13: INTERNAL | AE13: 1 | AO13: TM35 | AP13: N
A14: 011040M | B14: NEBAUTO | C14: Day 4 | D14: In Service | E14: F243 | F14: A300 | G14: F243 | H14: TRUE | I14: 45943.664 | J14: Auto Enrolment DC | L14: 603616 | M14: DC | P14: SecureShare Irish Li | Q14: DC | R14: 1 | S14: Auto Enrolment DC | T14: DC | U14: 45938.594 | V14: 45943.958 | W14: 1 | X14: 3.0700579 | Y14: ILFS Corporate Business | Z14: 25281CBPR02F85B | AA14: Google Ireland Limited | AB14: Completed | AC14: Employer: Google :: Number of Members: 1 | AD14: INTERNAL | AE14: 1 | AH14: Y337 | AI14: 45943.65 | AK14: Passed | AL14: Passed | AO14: TM32 | AP14: N
A15: 011045M | B15: NEBAUTO | C15: Day 1 | D15: In Service | E15: X967 | F15: NJ23 | G15: x967 | H15: TRUE | I15: 45938.624 | J15: Auto Enrolment DC | L15: 603640 | M15: DC | P15: SecureShare Irish Li | Q15: DC | R15: 1 | S15: Auto Enrolment DC | T15: DC | U15: 45938.599 | V15: 45943.958 | W15: 1 | X15: 0.025266204 | Y15: Unio Ltd | Z15: 25281CBPR02F8B0 | AA15: Petrogas Group Limited | AB15: Completed | AC15: Julius Majauskas | AD15: INTERNAL | AE15: 1 | AO15: TM35 | AP15: N
A16: 011049M | B16: NEBAUTO | C16: Day 2 | D16: In Service | E16: J905 | F16: A100 | G16: y939 | H16: TRUE | I16: 45940.44 | J16: Auto Enrolment DC | L16: 608020 | M16: DC | P16: SecureShare Irish Li | Q16: DC | R16: 1 | S16: Auto Enrolment DC | T16: DC | U16: 45938.601 | V16: 45943.958 | W16: 1 | X16: 1.8392824 | Y16: ILFS Corporate Business | Z16: 25281CBPR02F8F3 | AA16: Renaissance Services of Europe Limited | AB16: Completed | AC16: Employer: N/A :: Number of Members: N/A | AE16: 1 | AO16: TM05 | AP16: N
A17: 011053M | B17: NEBAUTO | C17: Day 1 | D17: In Service | E17: X967 | F17: NJ23 | G17: x967 | H17: TRUE | I17: 45938.627 | J17: Auto Enrolment DC | L17: 603640 | M17: DC | P17: SecureShare Irish Li | Q17: DC | R17: 1 | S17: Auto Enrolment DC | T17: DC | U17: 45938.604 | V17: 45943.958 | W17: 1 | X17: 0.022858796 | Y17: Unio Ltd | Z17: 25281CBPR02F92C | AA17: Petrogas Group Limited | AB17: Completed | AC17: Lina Rakauske | AD17: INTERNAL | AE17: 1 | AO17: TM35 | AP17: N
A18: 011054M | B18: NEBAUTO | C18: Day 2 | D18: In Service | E18: J987 | F18: A100 | G18: J987 | H18: TRUE | I18: 45940.503 | J18: Auto Enrolment DC | L18: 609862 | M18: DC | P18: SecureShare Irish Li | Q18: DC | R18: 1 | S18: Auto Enrolment DC | T18: DC | U18: 45938.606 | V18: 45943.958 | W18: 1 | X18: 1.8966088 | Y18: ILFS Corporate Business | Z18: 25281CBPR02F92E | AA18: Dunnes Stores Unlimited Company | AB18: Completed | AC18: Employer: Dunnes Stores :: Number of Members: 29 | AD18: INTERNAL | AE18: 1 | AO18: TM33 | AP18: N
A19: 011071M | B19: NESAUTO | C19: Day 3 | D19: In Service | E19: S143 | F19: A612 | G19: S143 | H19: TRUE | I19: 45943.492 | J19: Auto Enrolment DC | K19: 1201798 | L19: 609844 | M19: DC | P19: SecureShare Aon | Q19: DC | R19: 1 | S19: Auto Enrolment DC | T19: DC | U19: 45938.626 | V19: 45943.958 | W19: 1 | X19: 2.8659954 | Y19: Aon Ireland Ltd. | Z19: 25281CBPR02FB70 | AA19: Kitman Labs Limited | AB19: Completed | AC19: Deirbhile OCallaghan 1201798 | AD19: INTERNAL | AE19: 1 | AO19: TM01 | AP19: N
A20: 011072M | B20: NEBAUTO | C20: Day 3 | D20: In Service | E20: X967 | F20: A612 | G20: x967 | H20: TRUE | I20: 45940.721 | J20: Auto Enrolment DC | L20: 603485 | M20: DC | P20: SecureShare Coupa Op | Q20: DC | R20: 1 | S20: Auto Enrolment DC | T20: DC | U20: 45938.626 | V20: 45943.958 | W20: 1 | X20: 2.0944329 | Y20: Aon Ireland Ltd. | Z20: 25281CBPR02FB71 | AA20: Coupa Operations Inc. | AB20: Completed | AC20: Cristina Sala | AD20: INTERNAL | AE20: 1 | AO20: TM01 | AP20: N
A21: 011088M | B21: NESAUTO | C21: Day 3 | D21: In Service | E21: S143 | F21: S168 | G21: S143 | H21: TRUE | I21: 45943.486 | J21: Auto Enrolment DC | K21: 1201797 | L21: 602712 | M21: DC | P21: SecureShare Munster | Q21: DC | R21: 1 | S21: Auto Enrolment DC | T21: DC | U21: 45938.639 | V21: 45943.958 | W21: 1 | X21: 2.8475694 | Y21: Mercer (Elect Existing Business) | Z21: 25281CBPR02FC83 | AA21: MUNSTER CATTLE BREEDING GROUP LTD | AB21: Completed | AC21: Kieran Kelliher1201797 | AD21: INTERNAL | AE21: 1 | AO21: TM02 | AP21: N
A22: 011093M | B22: NEBAUTO | C22: Day 1 | D22: In Service | E22: X967 | F22: NJ23 | G22: x967 | H22: TRUE | I22: 45938.654 | J22: Auto Enrolment DC | L22: 603914 | M22: DC | P22: SecureShare Irish Li | Q22: DC | R22: 1 | S22: Auto Enrolment DC | T22: DC | U22: 45938.642 | V22: 45943.958 | W22: 1 | X22: 0.012546296 | Y22: Unio Ltd | Z22: 25281CBPR02FC84 | AA22: Capventis Limited | AB22: Completed | AC22: Stephen Bourke | AD22: INTERNAL | AE22: 1 | AO22: TM35 | AP22: N
A23: 011103M | B23: NESAUTO | C23: Day 4 | D23: In Service | E23: J987 | F23: TO66 | G23: J987 | H23: TRUE | I23: 45941.674 | J23: Auto Enrolment DC | K23: 1201726 | L23: 603633 | M23: DC | P23: PPI Secure Path | Q23: DC | R23: 1 | S23: Auto Enrolment DC | T23: DC | U23: 45938.65 | V23: 45943.958 | W23: 1 | X23: 3.0239815 | Y23: Mount Street Trustees Ltd | Z23: 25281CBPR02FCE7 | AA23: Nisbets Limited | AB23: Completed | AC23: Tony Slott | AD23: INTERNAL | AE23: 1 | AO23: TM05 | AP23: N
A24: 011105M | B24: NEBAUTO | C24: Day 5 + | D24: In Service | E24: J905 | F24: RM91 | G24: J905 | H24: TRUE | I24: 45946.605 | J24: Auto Enrolment DC | L24: 601157 | M24: DC | N24: 15 | P24: SecureShare Paddy De | Q24: DC | R24: 1 | S24: Auto Enrolment DC | T24: DC | U24: 45938.651 | V24: 45951.958 | W24: 1 | X24: 5.9540509 | Y24: Willis Towers Watson Life & Pensi | Z24: 25281CBPR02FDA3 | AA24: Paddy Denby Engineering Ltd | AB24: Completed | AC24: Employer: paddy denby engineering ltd :: Number of Members: 6 | AD24: INTERNAL | AE24: 1 | AO24: TM07 | AP24: N
A25: 011106M | B25: NESAUTO | C25: Day 4 | D25: In Service | E25: J905 | F25: TO66 | G25: J905 | H25: TRUE | I25: 45943.655 | J25: Auto Enrolment DC | K25: 1201490 | L25: 603633 | M25: DC | N25: 5 | P25: PPI Secure Path | Q25: DC | R25: 1 | S25: Auto Enrolment DC | T25: DC | U25: 45938.652 | V25: 45943.958 | W25: 1 | X25: 3.0030093 | Y25: Mount Street Trustees Ltd | Z25: 25281CBPR02FD14 | AA25: Nisbets Limited | AB25: Completed | AC25: Caroline Barry | AD25: INTERNAL | AE25: 1 | AH25: F243 | AI25: 45943.638 | AK25: Passed | AL25: Passed | AO25: TM05 | AP25: N
A26: 011109M | B26: NEBAUTO | C26: Day 2 | D26: In Service | E26: J905 | F26: RM91 | G26: y939 | H26: TRUE | I26: 45940.455 | J26: Auto Enrolment DC | L26: 602420 | M26: DC | P26: SecureShare WTW | Q26: DC | R26: 1 | S26: Auto Enrolment DC | T26: DC | U26: 45938.653 | V26: 45943.958 | W26: 1 | X26: 1.8019792 | Y26: Willis Towers Watson Life & Pensi | Z26: 25281CBPR02FE22 | AA26: Netgear International Limited | AB26: Completed | AC26: Employer: Net gear :: Number of Members: 1 | AD26: INTERNAL | AE26: 1 | AO26: TM07 | AP26: N
A27: 011110M | B27: NESAUTO | C27: Day 2 | D27: In Service | E27: J905 | F27: TO66 | G27: J905 | H27: TRUE | I27: 45940.426 | J27: Auto Enrolment DC | K27: 1201476 | L27: 603633 | M27: DC | N27: 5 | P27: PPI Secure Path | Q27: DC | R27: 1 | S27: Auto Enrolment DC | T27: DC | U27: 45938.655 | V27: 45943.958 | W27: 1 | X27: 1.7712616 | Y27: Mount Street Trustees Ltd | Z27: 25281CBPR02FD91 | AA27: Nisbets Limited | AB27: Completed | AC27: Nicole Bermingham | AD27: INTERNAL | AE27: 1 | AO27: TM05 | AP27: N
A28: 011114M | B28: NESAUTO | C28: Day 4 | D28: In Service | E28: J987 | F28: TO66 | G28: J987 | H28: TRUE | I28: 45941.666 | J28: Auto Enrolment DC | K28: 1201725 | L28: 603633 | M28: DC | P28: PPI Secure Path | Q28: DC | R28: 1 | S28: Auto Enrolment DC | T28: DC | U28: 45938.656 | V28: 45943.958 | W28: 1 | X28: 3.0104977 | Y28: Mount Street Trustees Ltd | Z28: 25281CBPR02FDD3 | AA28: Nisbets Limited | AB28: Completed | AC28: NE Rachel Lafferty | AD28: INTERNAL | AE28: 1 | AO28: TM05 | AP28: N
A29: 011125M | B29: NESAUTO | C29: Day 4 | D29: In Service | E29: J987 | F29: TO66 | G29: J987 | H29: TRUE | I29: 45941.684 | J29: Auto Enrolment DC | K29: 1201727 | L29: 603633 | M29: DC | P29: PPI Secure Path | Q29: DC | R29: 1 | S29: Auto Enrolment DC | T29: DC | U29: 45938.661 | V29: 45943.958 | W29: 1 | X29: 3.0229977 | Y29: Mount Street Trustees Ltd | Z29: 25281CBPR02FE77 | AA29: Nisbets Limited | AB29: Completed | AD29: INTERNAL | AE29: 1 | AO29: TM05 | AP29: N
A30: 011128M | B30: NESAUTO | C30: Day 4 | D30: In Service | E30: J987 | F30: TO66 | G30: J987 | H30: TRUE | I30: 45941.696 | J30: Auto Enrolment DC | L30: 603633 | M30: DC | P30: PPI Secure Path | Q30: DC | R30: 1 | S30: Auto Enrolment DC | T30: DC | U30: 45938.664 | V30: 45943.958 | W30: 1 | X30: 3.0316667 | Y30: Mount Street Trustees Ltd | Z30: 25281CBPR02FEBE | AA30: Nisbets Limited | AB30: Completed | AC30: Member Added 1201219 | AE30: 1 | AO30: TM05 | AP30: N
A31: 011140M | B31: NEBAUTO | C31: Day 3 | D31: In Service | E31: C192 | F31: A612 | G31: C192 | H31: TRUE | I31: 45943.625 | J31: Auto Enrolment DC | L31: 603524 | M31: DC | P31: SecureShare Irish Li | Q31: DC | R31: 1 | S31: Auto Enrolment DC | T31: DC | U31: 45938.677 | V31: 45943.958 | W31: 1 | X31: 2.9477431 | Y31: Aon Ireland Ltd. | Z31: 25281CBPR030080 | AA31: Riot Games Limited | AB31: Completed | AC31: Employer: N/A :: Number of Members: N/A | AE31: 1 | AH31: x967 | AI31: 45943.537 | AK31: Passed | AL31: Failed | AM31: Detail entered below (5) | AO31: TM12 | AP31: N
A32: 011154M | B32: NEBAUTO | C32: Day 2 | D32: In Service | E32: J905 | F32: A300 | G32: J905 | H32: TRUE | I32: 45940.493 | J32: Auto Enrolment DC | L32: 602377 | M32: DC | N32: 20 | P32: SecureShare Veolia U | Q32: DC | R32: 1 | S32: Auto Enrolment DC | T32: DC | U32: 45938.692 | V32: 45943.958 | W32: 1 | X32: 1.8005903 | Y32: ILFS Corporate Business | Z32: 25281CBPR030170 | AA32: Veolia Energy Ser Ireland Ltd | AB32: Completed | AC32: Employer: Veolia :: Number of Members: N/A | AD32: INTERNAL | AE32: 1 | AO32: TM05 | AP32: N
A33: 011155M | B33: NESAUTO | C33: Day 3 | D33: In Service | E33: S143 | F33: VT80 | G33: S143 | H33: TRUE | I33: 45943.475 | J33: Auto Enrolment DC | K33: 1201791 | L33: 603651 | M33: DC | P33: SecureShare Lockton | Q33: DC | R33: 1 | S33: Auto Enrolment DC | T33: DC | U33: 45938.693 | V33: 45943.958 | W33: 1 | X33: 2.7822106 | Y33: Lockton Insurance Brokers (Irelan | Z33: 25281CBPR0301A2 | AA33: Specialist Technical Engineering Serv. | AB33: Completed | AC33: Veronic McMahon 1201790 | AD33: INTERNAL | AE33: 1 | AO33: TM31 | AP33: N
A34: 011159M | B34: NEBAUTO | C34: Day 1 | D34: In Service | E34: X967 | F34: VO24 | G34: x967 | H34: TRUE | I34: 45938.765 | J34: Auto Enrolment DC | L34: 603358 | M34: DC | P34: SecureShare Irish Li | Q34: DC | R34: 1 | S34: Auto Enrolment DC | T34: DC | U34: 45938.7 | V34: 45943.958 | W34: 1 | X34: 0.065636574 | Y34: Bluechip Financial Consultants Lt | Z34: 25281CBPR0301D9 | AA34: Arachas Corporate Brokers Ltd | AB34: Completed | AC34: 24 x NE - Indexed World Eq Fund x 3 NE | AD34: INTERNAL | AE34: 1 | AO34: TM05 | AP34: N
A35: 011192M | B35: NEBAUTO | C35: Day 3 | D35: In Service | E35: x967 | F35: N847 | G35: C192 | H35: TRUE | I35: 45943.674 | J35: Auto Enrolment DC | L35: 603578 | M35: DC | P35: SecureShare Cathedra | Q35: DC | R35: 1 | S35: Auto Enrolment DC | T35: DC | U35: 45938.727 | V35: 45943.958 | W35: 1 | X35: 2.9474421 | Y35: Cathedral Financial Consultants L | Z35: 25281CBPR0302BD | AA35: Vow Europe Limited | AB35: Completed | AC35: Employer: Vow Europe Ltd :: Number of Members: 17 | AD35: INTERNAL | AE35: 1 | AH35: F243 | AI35: 45943.637 | AK35: Passed | AL35: Passed | AO35: TM07 | AP35: N
A36: 011196M | B36: NESAUTO | C36: Day 5 + | D36: In Service | E36: S143 | F36: RM91 | G36: S143 | H36: TRUE | I36: 45953.52 | J36: Auto Enrolment DC | K36: 1204206 | L36: 605271 | M36: DC | P36: SecureShare Datalec | Q36: DC | R36: 1 | S36: Auto Enrolment DC | T36: DC | U36: 45938.73 | V36: 45959.958 | W36: 1 | X36: 10.790012 | Y36: Willis Towers Watson Life & Pensi | Z36: 25281CBPR0302C9 | AA36: Datalec Precision Installations Limited | AB36: Completed | AC36: Joseph Iribhogbe 1204206 | AD36: INTERNAL | AE36: 1 | AO36: TM07 | AP36: N
A37: 011335M | B37: NESAUTO | C37: Day 3 | D37: In Service | E37: F243 | F37: RT02 | G37: F243 | H37: TRUE | I37: 45943.638 | J37: Auto Enrolment DC | K37: 1202034 | L37: 605381 | M37: DC | P37: SecureShare Castlehi | Q37: DC | R37: 1 | S37: Auto Enrolment DC | T37: DC | U37: 45939.343 | V37: 45946.958 | W37: 1 | X37: 2.2958333 | Y37: PWC Financial Consulting DAC | Z37: 25282CBPR03253A | AA37: Castlehitt Limited | AB37: Completed | AC37: Barry Burtler- Need salary | AD37: INTERNAL | AE37: 1 | AO37: TM01 | AP37: N
A38: 011341M | B38: NEBAUTO | C38: Day 4 | D38: In Service | E38: J905 | F38: E080 | G38: J905 | H38: TRUE | I38: 45944.516 | J38: Auto Enrolment DC | L38: 602375 | M38: DC | N38: 15 | P38: SecureShare Beacon H | Q38: DC | R38: 1 | S38: Auto Enrolment DC | T38: DC | U38: 45939.358 | V38: 45944.958 | W38: 1 | X38: 3.158044 | Y38: Mercer (Ireland) Limited | Z38: 25282CBPR0325AE | AA38: Beacon Hospital | AB38: Completed | AC38: Employer: N/A :: Number of Members: N/A | AD38: INTERNAL | AE38: 1 | AO38: TM12 | AP38: N
A39: 011352M | B39: NEBAUTO | C39: Day 4 | D39: In Service | E39: C192 | F39: A300 | G39: C192 | H39: TRUE | I39: 45944.655 | J39: Auto Enrolment DC | L39: 602903 | M39: DC | P39: SecureShare Brown Th | Q39: DC | R39: 1 | S39: Auto Enrolment DC | T39: DC | U39: 45939.378 | V39: 45944.958 | W39: 1 | X39: 3.2767824 | Y39: ILFS Corporate Business | Z39: 25282CBPR03266C | AA39: Brown Thomas Arnotts Limited | AB39: Completed | AC39: Employer: Brown Thomas Arnotts :: Number of Members: 4 | AD39: INTERNAL | AE39: 1 | AO39: TM05 | AP39: N
A40: 011355M | B40: NESAUTO | C40: Day 3 | D40: In Service | E40: F243 | F40: S168 | G40: F243 | H40: TRUE | I40: 45941.473 | J40: Auto Enrolment DC | K40: 1201699 | L40: 602944 | M40: DC | P40: SecureShare Patrick | Q40: DC | R40: 1 | S40: Auto Enrolment DC | T40: DC | U40: 45939.387 | V40: 45944.958 | W40: 1 | X40: 2.0867708 | Y40: Mercer (Elect Existing Business) | Z40: 25282CBPR03272C | AA40: PATRICK J TOBIN LTD | AB40: Completed | AC40: Saoirse Burke | AD40: INTERNAL | AE40: 1 | AO40: TM01 | AP40: N
A41: 011356M | B41: NESAUTO | C41: Day 3 | D41: In Service | E41: F243 | F41: S168 | G41: F243 | H41: TRUE | I41: 45941.471 | J41: Auto Enrolment DC | K41: 1201700 | L41: 602944 | M41: DC | P41: SecureShare Patrick | Q41: DC | R41: 1 | S41: Auto Enrolment DC | T41: DC | U41: 45939.387 | V41: 45944.958 | W41: 1 | X41: 2.0835764 | Y41: Mercer (Elect Existing Business) | Z41: 25282CBPR03272D | AA41: PATRICK J TOBIN LTD | AB41: Completed | AC41: Ronald Munetsi | AD41: INTERNAL | AE41: 1 | AO41: TM01 | AP41: N
A42: 011357M | B42: NESAUTO | C42: Day 3 | D42: In Service | E42: F243 | F42: S168 | G42: F243 | H42: TRUE | I42: 45941.473 | J42: Auto Enrolment DC | K42: 1201701 | L42: 602944 | M42: DC | P42: SecureShare Patrick | Q42: DC | R42: 1 | S42: Auto Enrolment DC | T42: DC | U42: 45939.387 | V42: 45944.958 | W42: 1 | X42: 2.0852894 | Y42: Mercer (Elect Existing Business) | Z42: 25282CBPR03272A | AA42: PATRICK J TOBIN LTD | AB42: Completed | AC42: Leandro Benedik | AD42: INTERNAL | AE42: 1 | AO42: TM01 | AP42: N
A43: 011358M | B43: NESAUTO | C43: Day 3 | D43: In Service | E43: F243 | F43: S168 | G43: F243 | H43: TRUE | I43: 45941.446 | J43: Auto Enrolment DC | K43: 1201698 | L43: 602944 | M43: DC | P43: SecureShare Patrick | Q43: DC | R43: 1 | S43: Auto Enrolment DC | T43: DC | U43: 45939.388 | V43: 45944.958 | W43: 1 | X43: 2.0586806 | Y43: Mercer (Elect Existing Business) | Z43: 25282CBPR03272E | AA43: PATRICK J TOBIN LTD | AB43: Completed | AC43: Taryn Lee Anne Keane | AD43: INTERNAL | AE43: 1 | AO43: TM01 | AP43: N
A44: 011359M | B44: NEBAUTO | C44: Day 3 | D44: In Service | E44: X967 | F44: A612 | G44: x967 | H44: TRUE | I44: 45943.495 | J44: Auto Enrolment DC | L44: 606934 | M44: DC | P44: SecureShare Apleona | Q44: DC | R44: 1 | S44: Auto Enrolment DC | T44: DC | U44: 45939.39 | V44: 45944.958 | W44: 1 | X44: 2.1045949 | Y44: Aon Ireland Ltd. | Z44: 25282CBPR032776 | AA44: Apleona Ireland Limited | AB44: Completed | AC44: Employer: Apleona Ireland Ltd :: Number of Members: Jack Large | AD44: INTERNAL | AE44: 1 | AO44: TM01 | AP44: N
A45: 011362M | B45: NESAUTO | C45: Day 4 | D45: In Service | E45: Y337 | F45: TU84 | G45: Y337 | H45: TRUE | I45: 45944.43 | J45: Auto Enrolment DC | K45: 1202252 | L45: 609841 | M45: DC | P45: SecureShare Blackroc | Q45: DC | R45: 1 | S45: Auto Enrolment DC | T45: DC | U45: 45939.393 | V45: 45944.958 | W45: 1 | X45: 3.0372106 | Y45: Joseph G. Byrne & Sons Consulting | Z45: 25282CBPR032775 | AA45: Galway Clinic Doughiska Unltd Co | AB45: Completed | AC45: Maura Spring - added 1202252 | AD45: INTERNAL | AE45: 1 | AO45: TM32 | AP45: N
A46: 011383M | B46: NEBAUTO | C46: Day 1 | D46: In Service | E46: J905 | F46: RN10 | G46: J905 | H46: TRUE | I46: 45939.494 | J46: Auto Enrolment DC | L46: 602032 | M46: DC | N46: 15 | P46: SecureShare Irish Li | Q46: DC | R46: 1 | S46: Auto Enrolment DC | T46: DC | U46: 45939.403 | V46: 45944.958 | W46: 1 | X46: 0.091076389 | Y46: Unio (L&P) | Z46: 25282CBPR032857 | AA46: Presentation Brothers (Ireland) | AB46: Completed | AC46: Employer: N/A :: Number of Members: N/A | AD46: INTERNAL | AE46: 1 | AO46: TM35 | AP46: N
A47: 011388M | B47: NEBAUTO | C47: Day 1 | D47: In Service | E47: X967 | F47: RS60 | G47: x967 | H47: TRUE | I47: 45939.48 | J47: Auto Enrolment DC | L47: 602408 | M47: DC | P47: SecureShare Irish Li | Q47: DC | R47: 1 | S47: Auto Enrolment DC | T47: DC | U47: 45939.411 | V47: 45944.958 | W47: 1 | X47: 0.06912037 | Y47: Unio (CCC) | Z47: 25282CBPR0328E2 | AA47: Aimware Limited | AB47: Completed | AC47: John Lamphiere | AD47: INTERNAL | AE47: 1 | AO47: TM35 | AP47: N
A48: 011390M | B48: NEBAUTO | C48: Day 4 | D48: In Service | E48: J905 | F48: A100 | G48: J905 | H48: TRUE | I48: 45944.421 | J48: Auto Enrolment DC | L48: 605268 | M48: DC | N48: 15 | P48: SecureShare Project | Q48: DC | R48: 1 | S48: Auto Enrolment DC | T48: DC | U48: 45939.415 | V48: 45944.958 | W48: 1 | X48: 3.0060764 | Y48: ILFS Corporate Business | Z48: 25282CBPR032956 | AA48: Project Management Limited | AB48: Completed | AC48: Employer: N/A :: Number of Members: N/A | AD48: INTERNAL | AE48: 1 | AO48: TM33 | AP48: N
A49: 011391M | B49: NESAUTO | C49: Day 3 | D49: In Service | E49: J905 | F49: E080 | G49: J905 | H49: TRUE | I49: 45943.446 | J49: Auto Enrolment DC | K49: 1201774 | L49: 602719 | M49: DC | N49: 5 | P49: SecureShare Roadston | Q49: DC | R49: 1 | S49: Auto Enrolment DC | T49: DC | U49: 45939.419 | V49: 45944.958 | W49: 1 | X49: 2.0273264 | Y49: Mercer (Ireland) Limited | Z49: 25282CBPR032989 | AA49: Roadstone Limited | AB49: Completed | AC49: Employer: Roadstone Ltd :: Member Name: Mr Joshua McAnaspie :: Date of Birth: 28/10/1998 | AD49: INTERNAL | AE49: 1 | AO49: TM12 | AP49: N
A50: 011392M | B50: NEBAUTO | C50: Day 4 | D50: In Service | E50: J905 | F50: VW22 | G50: J905 | H50: TRUE | I50: 45944.441 | J50: Auto Enrolment DC | L50: 603783 | M50: DC | P50: SecureShare Irish Li | Q50: DC | R50: 1 | S50: Auto Enrolment DC | T50: DC | U50: 45939.419 | V50: 45944.958 | W50: 1 | X50: 3.0223032 | Y50: Hastings Life & Pensions Ltd | Z50: 25282CBPR03298A | AA50: Kverneland Group Ireland Limited | AB50: Completed | AC50: member has been added 1200050 | AD50: INTERNAL | AE50: 1 | AO50: TM07 | AP50: N
A51: 011396M | B51: NEBAUTO | C51: Out of Service | D51: Out of Service | E51: F243 | F51: 4390 | G51: F243 | H51: TRUE | I51: 45945.387 | J51: Auto Enrolment DC | L51: 609743 | M51: DC | P51: SecureShare Irish Li | Q51: DC | R51: 1 | S51: Auto Enrolment DC | T51: DC | U51: 45939.426 | V51: 45944.958 | W51: 1 | X51: 3.9619097 | Y51: Eileen Gillick | Z51: 25282CBPR032A14 | AA51: Motorola Solutions UK Ltd (Irl Branch) | AB51: Completed | AC51: Employer: Motorola Solutions UK :: Number of Members: 8 | AD51: INTERNAL | AE51: 1 | AH51: F243 | AI51: 45945.382 | AK51: Passed | AL51: Passed | AO51: TM05 | AP51: N
A52: 011400M | B52: NEBAUTO | C52: Day 1 | D52: In Service | E52: H506 | F52: TQ49 | G52: H506 | H52: TRUE | I52: 45939.465 | J52: Auto Enrolment DC | L52: 603612 | M52: DC | N52: 20 | P52: SecureShare Irish Li | Q52: DC | R52: 1 | S52: Auto Enrolment DC | T52: DC | U52: 45939.43 | V52: 45944.958 | W52: 1 | X52: 0.035011574 | Y52: City Life Financial Services Ltd. | Z52: 25282CBPR032A55 | AA52: Stauntons Pharmacy Limited | AB52: Completed | AC52: x2 NEs Added | AD52: INTERNAL | AE52: 1 | AO52: TM07 | AP52: N
A53: 011406M | B53: NEBAUTO | C53: Out of Service | D53: Out of Service | E53: F243 | F53: TA22 | G53: F243 | H53: TRUE | I53: 45945.388 | J53: Auto Enrolment DC | L53: 609755 | M53: DC | P53: SecureShare Irish Li | Q53: DC | R53: 1 | S53: Auto Enrolment DC | T53: DC | U53: 45939.433 | V53: 45944.958 | W53: 1 | X53: 3.9551505 | Y53: RBK Business Services Ltd | Z53: 25282CBPR032AA0 | AA53: MSL Healthcare Ltd | AB53: Completed | AC53: Employer: MSL Healthcare :: Number of Members: 1 | AD53: INTERNAL | AE53: 1 | AH53: F243 | AI53: 45945.382 | AK53: Passed | AL53: Passed | AO53: TM07 | AP53: N
A54: 011407M | B54: NEBAUTO | C54: Day 2 | D54: In Service | E54: X465 | F54: NE65 | G54: X465 | H54: TRUE | I54: 45940.496 | J54: Auto Enrolment DC | L54: 608028 | M54: DC | P54: SecureShare Irish Li | Q54: DC | R54: 1 | S54: Auto Enrolment DC | T54: DC | U54: 45939.434 | V54: 45944.958 | W54: 1 | X54: 1.0613773 | Y54: Hewitt Associates Limited | Z54: 25282CBPR032AA1 | AA54: Apple | AB54: Completed | AC54: Employer: Apple :: Number of Members: 6 | AE54: 1 | AH54: X465 | AI54: 45940.493 | AK54: Passed | AL54: Passed | AO54: TM32 | AP54: N
A55: 011436M | B55: NEBAUTO | C55: Day 3 | D55: In Service | E55: J905 | F55: A612 | G55: J905 | H55: TRUE | I55: 45944.429 | J55: Auto Enrolment DC | L55: 605239 | M55: DC | N55: 10 | P55: SecureShare Arctera | Q55: DC | R55: 1 | S55: Auto Enrolment DC | T55: DC | U55: 45939.479 | V55: 45944.958 | W55: 1 | X55: 2.949375 | Y55: Aon Ireland Ltd. | Z55: 25282CBPR032E67 | AA55: Arctera International Limited | AB55: Completed | AC55: Employer: N/A :: Number of Members: 3 | AD55: INTERNAL | AE55: 1 | AO55: TM01 | AP55: N
A56: 011443M | B56: NEBAUTO | C56: Day 1 | D56: In Service | E56: H506 | F56: VS41 | G56: H506 | H56: TRUE | I56: 45939.506 | J56: Auto Enrolment DC | L56: 605064 | M56: DC | N56: 20 | P56: SecureShare Irish Li | Q56: DC | R56: 1 | S56: Auto Enrolment DC | T56: DC | U56: 45939.484 | V56: 45944.958 | W56: 1 | X56: 0.022789352 | Y56: NFP Ireland Consultants Ltd | Z56: 25282CBPR032EEA | AA56: Bristow Ireland Limited | AB56: Completed | AC56: x1 NE Added | AD56: INTERNAL | AE56: 1 | AO56: TM07 | AP56: N
A57: 011470M | B57: NESAUTO | C57: Day 3 | D57: In Service | E57: S143 | F57: A612 | G57: S143 | H57: TRUE | I57: 45944.412 | J57: Auto Enrolment DC | K57: 1202232 | L57: 606951 | M57: DC | P57: SecureShare Aon | Q57: DC | R57: 1 | S57: Auto Enrolment DC | T57: DC | U57: 45939.502 | V57: 45944.958 | W57: 1 | X57: 2.9096296 | Y57: Aon Ireland Ltd. | Z57: 25282CBPR0330FC | AA57: Boxever Limited | AB57: Completed | AC57: Lisenko Nikolla 1202232 | AD57: INTERNAL | AE57: 1 | AO57: TM01 | AP57: N
A58: 011491M | B58: NEBAUTO | C58: Day 3 | D58: In Service | E58: X967 | F58: A612 | G58: x967 | H58: TRUE | I58: 45944.455 | J58: Auto Enrolment DC | L58: 609839 | M58: DC | P58: SecureShare Aon | Q58: DC | R58: 1 | S58: Auto Enrolment DC | T58: DC | U58: 45939.519 | V58: 45944.958 | W58: 1 | X58: 2.9364005 | Y58: Aon Ireland Ltd. | Z58: 25282CBPR03329E | AA58: Viatris Pension Plan | AB58: Completed | AC58: Duplicate - Number of Members: 5 | AE58: 1 | AO58: TM01 | AP58: N
A59: 011492M | B59: NEBAUTO | C59: Day 1 | D59: In Service | E59: X967 | F59: NJ24 | G59: x967 | H59: TRUE | I59: 45939.532 | J59: Auto Enrolment DC | L59: 606850 | M59: DC | P59: SecureShare Irish Li | Q59: DC | R59: 1 | S59: Auto Enrolment DC | T59: DC | U59: 45939.519 | V59: 45944.958 | W59: 1 | X59: 0.012627315 | Y59: Unio (BONDS) | Z59: 25282CBPR03329D | AA59: Tente Limited Employee Benefits Plan | AB59: Completed | AC59: James Clarke | AD59: INTERNAL | AE59: 1 | AO59: TM34 | AP59: N
A60: 011493M | B60: NESAUTO | C60: Day 3 | D60: In Service | E60: S143 | F60: NJ23 | G60: S143 | H60: TRUE | I60: 45944.417 | J60: Auto Enrolment DC | K60: 1202235 | L60: 602656 | M60: DC | P60: SecureShare Unio Emp | Q60: DC | R60: 1 | S60: Auto Enrolment DC | T60: DC | U60: 45939.52 | V60: 45944.958 | W60: 1 | X60: 2.8971991 | Y60: Unio Ltd | Z60: 25282CBPR033306 | AA60: Horse Sport Ireland Ltd | AB60: Completed | AC60: Aoife Carr 1202235 | AD60: INTERNAL | AE60: 1 | AO60: TM35 | AP60: N
A61: 011510M | B61: NEBAUTO | C61: Day 3 | D61: In Service | E61: J905 | F61: S168 | G61: J905 | H61: TRUE | I61: 45944.436 | J61: Auto Enrolment DC | L61: 603754 | M61: DC | N61: 10 | P61: SecureShare GoTo Tec | Q61: DC | R61: 1 | S61: Auto Enrolment DC | T61: DC | U61: 45939.534 | V61: 45944.958 | W61: 1 | X61: 2.9019097 | Y61: Mercer (Elect Existing Business) | Z61: 25282CBPR0333FB | AA61: GoTo Technologies Ireland Unlimited Co. | AB61: Completed | AC61: Employer: GoTo Technology Ireland Unlimited Co :: Number of Members: 2 | AD61: INTERNAL | AE61: 1 | AO61: TM01 | AP61: N
A62: 011526M | B62: NESAUTO | C62: Day 5 + | D62: In Service | E62: F243 | F62: S168 | G62: F243 | H62: TRUE | I62: 45951.494 | J62: Auto Enrolment DC | K62: 1203769 | L62: 601397 | M62: DC | P62: SecureShare Tokyo El | Q62: DC | R62: 1 | S62: Auto Enrolment DC | T62: DC | U62: 45939.546 | V62: 45954.958 | W62: 1 | X62: 7.9482755 | Y62: Mercer (Elect Existing Business) | Z62: 25282CBPR0334F3 | AA62: Tokyo Electron Europe Ltd | AB62: Completed | AC62: Julian Van Zijl- ER details confirmed | AD62: INTERNAL | AE62: 1 | AO62: TM02 | AP62: N
A63: 011531M | B63: NESAUTO | C63: Day 2 | D63: In Service | E63: F243 | F63: S168 | G63: F243 | H63: TRUE | I63: 45941.442 | J63: Auto Enrolment DC | K63: 1201697 | L63: 601397 | M63: DC | P63: SecureShare Tokyo El | Q63: DC | R63: 1 | S63: Auto Enrolment DC | T63: DC | U63: 45939.552 | V63: 45944.958 | W63: 1 | X63: 1.8899074 | Y63: Mercer (Elect Existing Business) | Z63: 25282CBPR033539 | AA63: Tokyo Electron Europe Ltd | AB63: Completed | AC63: Ahmad Rizal Ahmad Nor | AD63: INTERNAL | AE63: 1 | AO63: TM02 | AP63: N
A64: 011534M | B64: NEBAUTO | C64: Day 3 | D64: In Service | E64: J905 | F64: VW22 | G64: J905 | H64: TRUE | I64: 45943.655 | J64: Auto Enrolment DC | L64: 603768 | M64: DC | N64: 10 | P64: SecureShare Irish Li | Q64: DC | R64: 1 | S64: Auto Enrolment DC | T64: DC | U64: 45939.554 | V64: 45944.958 | W64: 1 | X64: 2.1005671 | Y64: Hastings Life & Pensions Ltd | Z64: 25282CBPR03359E | AA64: Natures Best Limited | AB64: Completed | AC64: Frances Haddane | AD64: INTERNAL | AE64: 1 | AH64: F243 | AI64: 45943.638 | AK64: Passed | AL64: Passed | AO64: TM07 | AP64: N
A65: 011536M | B65: NESAUTO | C65: Day 2 | D65: In Service | E65: F243 | F65: S168 | G65: F243 | H65: TRUE | I65: 45941.44 | J65: Auto Enrolment DC | K65: 1201696 | L65: 601397 | M65: DC | P65: SecureShare Tokyo El | Q65: DC | R65: 1 | S65: Auto Enrolment DC | T65: DC | U65: 45939.555 | V65: 45944.958 | W65: 1 | X65: 1.8846759 | Y65: Mercer (Elect Existing Business) | Z65: 25282CBPR03359D | AA65: Tokyo Electron Europe Ltd | AB65: Completed | AC65: Karl Derwin | AD65: INTERNAL | AE65: 1 | AO65: TM02 | AP65: N
A66: 011560M | B66: NEBAUTO | C66: Day 1 | D66: In Service | E66: J905 | F66: S168 | G66: J905 | H66: TRUE | I66: 45939.67 | J66: Auto Enrolment DC | L66: 606821 | M66: DC | N66: 45 | P66: SecureShare Irish Li | Q66: DC | R66: 1 | S66: Auto Enrolment DC | T66: DC | U66: 45939.58 | V66: 45944.958 | W66: 1 | X66: 0.089965278 | Y66: Mercer (Elect Existing Business) | Z66: 25282CBPR033773 | AA66: Siemens Energy Ireland Limited | AB66: Completed | AC66: Employer: N/A :: Number of Members: N/A | AD66: INTERNAL | AE66: 1 | AO66: TM01 | AP66: N
A67: 011575M | B67: NEBAUTO | C67: Day 3 | D67: In Service | E67: X465 | F67: NE65 | G67: X465 | H67: TRUE | I67: 45944.591 | J67: Auto Enrolment DC | L67: 608028 | M67: DC | P67: SecureShare Irish Li | Q67: DC | R67: 1 | S67: Auto Enrolment DC | T67: DC | U67: 45939.593 | V67: 45944.958 | W67: 1 | X67: 2.9977546 | Y67: Hewitt Associates Limited | Z67: 25282CBPR033877 | AA67: Apple | AB67: Completed | AC67: Employer: Apple (13 ADIM 5 AOEW) :: Number of Members: 18 | AD67: INTERNAL | AE67: 1 | AH67: Y337 | AI67: 45944.502 | AK67: Passed | AL67: Passed | AO67: TM32 | AP67: N
A68: 011580M | B68: NEBAUTO | C68: Day 4 | D68: In Service | E68: X967 | F68: A300 | G68: x967 | H68: TRUE | I68: 45944.62 | J68: Auto Enrolment DC | L68: 603525 | M68: DC | P68: SecureShare Irish Li | Q68: DC | R68: 1 | S68: Auto Enrolment DC | T68: DC | U68: 45939.596 | V68: 45944.958 | W68: 1 | X68: 3.0240162 | Y68: ILFS Corporate Business | Z68: 25282CBPR0338DC | AA68: National Advocacy Service | AB68: Completed | AC68: 2 x NE | AD68: INTERNAL | AE68: 1 | AO68: TM05 | AP68: N
A69: 011597M | B69: NEBAUTO | C69: Day 3 | D69: In Service | E69: C192 | F69: S168 | G69: C192 | H69: TRUE | I69: 45944.579 | J69: Auto Enrolment DC | L69: 603965 | M69: DC | P69: SecureShare Toasttab | Q69: DC | R69: 1 | S69: Auto Enrolment DC | T69: DC | U69: 45939.613 | V69: 45944.958 | W69: 1 | X69: 2.9658102 | Y69: Mercer (Elect Existing Business) | Z69: 25282CBPR033AF4 | AA69: Toasttab Ireland Limited | AB69: Completed | AC69: Employer: N/A :: Number of Members: N/A | AD69: INTERNAL | AE69: 1 | AO69: TM12 | AP69: N
A70: 011615M | B70: NEBAUTO | C70: Day 3 | D70: In Service | E70: J905 | F70: A100 | G70: J905 | H70: TRUE | I70: 45944.603 | J70: Auto Enrolment DC | L70: 609970 | M70: DC | N70: 45 | P70: SecureShare BearingP | Q70: DC | R70: 1 | S70: Auto Enrolment DC | T70: DC | U70: 45939.628 | V70: 45944.958 | W70: 1 | X70: 2.975081 | Y70: ILFS Corporate Business | Z70: 25282CBPR033CB4 | AA70: BearingPoint Ireland Limited | AB70: Completed | AC70: Employer: BearingPoint :: Number of Members: 40 | AD70: INTERNAL | AE70: 1 | AO70: TM05 | AP70: N
A71: 011617M | B71: NESAUTO | C71: Day 3 | D71: In Service | E71: Y337 | F71: TU84 | G71: Y337 | H71: TRUE | I71: 45944.445 | J71: Auto Enrolment DC | K71: 1202292 | L71: 609841 | M71: DC | P71: SecureShare Blackroc | Q71: DC | R71: 1 | S71: Auto Enrolment DC | T71: DC | U71: 45939.629 | V71: 45944.958 | W71: 1 | X71: 2.816331 | Y71: Joseph G. Byrne & Sons Consulting | Z71: 25282CBPR033CB3 | AA71: Galway Clinic Doughiska Unltd Co | AB71: Completed | AC71: Ann Maria Tom - added 1202292 | AD71: INTERNAL | AE71: 1 | AO71: TM32 | AP71: N
A72: 011619M | B72: NEBAUTO | C72: Day 2 | D72: In Service | E72: K526 | F72: RM91 | G72: y939 | H72: TRUE | I72: 45940.68 | J72: Auto Enrolment DC | L72: 603691 | M72: DC | P72: SecureShare WTW | Q72: DC | R72: 1 | S72: Auto Enrolment DC | T72: DC | U72: 45939.63 | V72: 45944.958 | W72: 1 | X72: 1.0506713 | Y72: Willis Towers Watson Life & Pensi | Z72: 25282CBPR033D10 | AA72: Palo Alto Security Limited | AB72: Completed | AC72: Employer: Palo Alto :: Number of Members: 2 | AD72: INTERNAL | AE72: 1 | AO72: TM07 | AP72: N
A73: 011621M | B73: NEBAUTO | C73: Out of Service | D73: Out of Service | E73: C192 | F73: S168 | G73: C192 | H73: TRUE | I73: 45945.441 | J73: Auto Enrolment DC | L73: 602944 | M73: DC | P73: SecureShare Patrick | Q73: DC | R73: 1 | S73: Auto Enrolment DC | T73: DC | U73: 45939.632 | V73: 45944.958 | W73: 1 | X73: 3.8087153 | Y73: Mercer (Elect Existing Business) | Z73: 25282CBPR033D0F | AA73: PATRICK J TOBIN LTD | AB73: Completed | AC73: 5 members already active, added : Naicker Esaivani | AD73: INTERNAL | AE73: 1 | AH73: C192 | AI73: 45944.738 | AK73: Passed | AL73: Passed | AM73: Detail entered below (5) | AO73: TM01 | AP73: N
A74: 011645M | B74: NESAUTO | C74: Day 3 | D74: In Service | E74: C192 | F74: NH05 | G74: C192 | H74: TRUE | I74: 45944.583 | J74: Auto Enrolment DC | K74: 1202350 | L74: 601479 | M74: DC | P74: SecureShare Moneywis | Q74: DC | R74: 1 | S74: Auto Enrolment DC | T74: DC | U74: 45939.65 | V74: 45944.958 | W74: 1 | X74: 2.9336806 | Y74: Moneywise Financial Planning Ltd | Z74: 25282CBPR033EB0 | AA74: ByrneWallace RS Plan | AB74: Completed | AC74: Employer: ByrneWallace :: Member Name: Sinead Egan :: Date of Birth: 30/11/1985 | AD74: INTERNAL | AE74: 1 | AO74: TM31 | AP74: N
A75: 011683M | B75: NESAUTO | C75: Day 3 | D75: In Service | E75: S143 | F75: D735 | G75: S143 | H75: TRUE | I75: 45944.427 | J75: Auto Enrolment DC | K75: 1202246 | L75: 603833 | M75: DC | P75: SecureShare IHI Grou | Q75: DC | R75: 1 | S75: Auto Enrolment DC | T75: DC | U75: 45939.698 | V75: 45944.958 | W75: 1 | X75: 2.728588 | Y75: NFP Ireland Consultants Ltd | Z75: 25282CBPR0342F3 | AA75: Keeper Security EMEA Limited | AB75: Completed | AC75: Michael Deloughry 1202246 | AD75: INTERNAL | AE75: 1 | AO75: TM07 | AP75: N
A76: 011697M | B76: NEBAUTO | C76: Out of Service | D76: Out of Service | E76: F243 | F76: NJ24 | G76: F243 | H76: TRUE | I76: 45945.387 | J76: Auto Enrolment DC | L76: 606901 | M76: DC | P76: SecureShare Killarne | Q76: DC | R76: 1 | S76: Auto Enrolment DC | T76: DC | U76: 45939.706 | V76: 45944.958 | W76: 1 | X76: 3.6812153 | Y76: Unio (BONDS) | Z76: 25282CBPR03437A | AA76: Killarney Hotels Limited | AB76: Completed | AC76: Employer: Killarney Hotels Ltd. :: Number of Members: 1 | AD76: INTERNAL | AE76: 1 | AH76: F243 | AI76: 45945.382 | AK76: Passed | AL76: Passed | AO76: TM34 | AP76: N
A77: 011702M | B77: NESAUTO | C77: Day 3 | D77: In Service | E77: x967 | F77: NJ23 | G77: x967 | H77: TRUE | I77: 45944.69 | J77: Auto Enrolment DC | K77: 1202405 | L77: 603165 | M77: DC | P77: SecureShare Ethos En | Q77: DC | R77: 1 | S77: Auto Enrolment DC | T77: DC | U77: 45939.711 | V77: 45944.958 | W77: 1 | X77: 2.9781481 | Y77: Unio Ltd | Z77: 25282CBPR0343AE | AA77: Ethos Engineering Limited | AB77: Completed | AC77: Darren Munn (see attached file for full description) | AD77: INTERNAL | AE77: 1 | AO77: TM35 | AP77: N
A78: 011703M | B78: NEBAUTO | C78: Day 3 | D78: In Service | E78: J905 | F78: VO82 | G78: J905 | H78: TRUE | I78: 45944.56 | J78: Auto Enrolment DC | L78: 602254 | M78: DC | N78: 20 | P78: SecureShare East Cor | Q78: DC | R78: 1 | S78: Auto Enrolment DC | T78: DC | U78: 45939.714 | V78: 45944.958 | W78: 1 | X78: 2.8455208 | Y78: Chartered Life Wealth Management | Z78: 25282CBPR0343C6 | AA78: East Cork Oil Company Unlimited Company | AB78: Completed | AC78: Employer: East Cork Oil :: Number of Members: 1 | AD78: INTERNAL | AE78: 1 | AO78: TM07 | AP78: N
A79: 011722M | B79: NEBAUTO | C79: Day 3 | D79: In Service | E79: X967 | F79: VP38 | G79: x967 | H79: TRUE | I79: 45944.609 | J79: Auto Enrolment DC | L79: 606859 | M79: DC | P79: SecureShare Opening | Q79: DC | R79: 1 | S79: Auto Enrolment DC | T79: DC | U79: 45939.756 | V79: 45944.958 | W79: 1 | X79: 2.8528472 | Y79: Lockton Insurance Brokers (Irelan | Z79: 25282CBPR0344A7 | AA79: Opening HR Limited | AB79: Completed | AC79: Employer: HR OPENING :: Number of Members: Oisin Skinnador | AD79: INTERNAL | AE79: 1 | AO79: TM05 | AP79: N
A80: 011902M | B80: NEBAUTO | C80: Day 1 | D80: In Service | E80: J987 | F80: A300 | G80: J987 | H80: TRUE | I80: 45940.48 | J80: Auto Enrolment DC | L80: 603658 | M80: DC | P80: SecureShare Smartply | Q80: DC | R80: 1 | S80: Auto Enrolment DC | T80: DC | U80: 45940.332 | V80: 45944.958 | W80: 1 | X80: 0.14790509 | Y80: ILFS Corporate Business | Z80: 25283CBPR035080 | AA80: Smartply Europe DAC | AB80: Completed | AC80: Member Added | AE80: 1 | AO80: TM05 | AP80: N
A81: 011920M | B81: NEBAUTO | C81: Day 3 | D81: In Service | E81: Y337 | F81: A300 | G81: Y337 | H81: TRUE | I81: 45944.385 | J81: Auto Enrolment DC | L81: 609707 | M81: DC | P81: SecureShare Waterfor | Q81: DC | R81: 1 | S81: Auto Enrolment DC | T81: DC | U81: 45940.381 | V81: 45945.958 | W81: 1 | X81: 2.0041204 | Y81: ILFS Corporate Business | Z81: 25283CBPR0351FF | AA81: NFVSP Waterford Intellectual Disability | AB81: Completed | AC81: 1 NE N/A :: Number of Members: 1 | AD81: INTERNAL | AE81: 1 | AO81: TM32 | AP81: N
A82: 011928M | B82: NEBAUTO | C82: Day 4 | D82: In Service | E82: Y337 | F82: A100 | G82: Y337 | H82: TRUE | I82: 45945.49 | J82: Auto Enrolment DC | L82: 602166 | M82: DC | P82: SecureShare St Vince | Q82: DC | R82: 1 | S82: Auto Enrolment DC | T82: DC | U82: 45940.39 | V82: 45945.958 | W82: 1 | X82: 3.1005903 | Y82: ILFS Corporate Business | Z82: 25283CBPR035247 | AA82: St Vincent's Private Hospital | AB82: Completed | AC82: 31 NEs St Vincent's Private Hospital :: Number of Members: 31 | AD82: INTERNAL | AE82: 1 | AO82: TM33 | AP82: N
A83: 011943M | B83: NEBAUTO | C83: Day 5 + | D83: In Service | E83: J905 | F83: S168 | G83: J905 | H83: TRUE | I83: 45947.663 | J83: Auto Enrolment DC | L83: 602392 | M83: DC | P83: SecureShare Gowan Gr | Q83: DC | R83: 1 | S83: Auto Enrolment DC | T83: DC | U83: 45940.406 | V83: 45951.958 | W83: 1 | X83: 5.2565509 | Y83: Mercer (Elect Existing Business) | Z83: 25283CBPR03536E | AA83: Gowan Group Ltd | AB83: Completed | AC83: all members added | AD83: INTERNAL | AE83: 1 | AO83: TM12 | AP83: N
A84: 011946M | B84: NEBAUTO | C84: Day 4 | D84: In Service | E84: J905 | F84: NT07 | G84: J905 | H84: TRUE | I84: 45945.436 | J84: Auto Enrolment DC | L84: 606866 | M84: DC | N84: 10 | P84: SecureShare MeiraGTx | Q84: DC | R84: 1 | S84: Auto Enrolment DC | T84: DC | U84: 45940.409 | V84: 45945.958 | W84: 1 | X84: 3.0273958 | Y84: Unio | Z84: 25283CBPR0353A1 | AA84: MeiraGTX Ireland DAC | AB84: Completed | AC84: Employer: MeiraGTx Ireland DAC. :: Number of Members: N/A | AD84: INTERNAL | AE84: 1 | AO84: TM35 | AP84: N
A85: 011956M | B85: NEBAUTO | C85: Day 1 | D85: In Service | E85: X967 | F85: NJ24 | G85: x967 | H85: TRUE | I85: 45940.526 | J85: Auto Enrolment DC | L85: 609914 | M85: DC | P85: SecureShare Irish Li | Q85: DC | R85: 1 | S85: Auto Enrolment DC | T85: DC | U85: 45940.419 | V85: 45945.958 | W85: 1 | X85: 0.10733796 | Y85: Unio (BONDS) | Z85: 25283CBPR03542B | AA85: Agri Health DC Pension Scheme | AB85: Completed | AC85: 3 x NE Self Directed Funds | AD85: INTERNAL | AE85: 1 | AO85: TM34 | AP85: N
A86: 011958M | B86: NEBAUTO | C86: Day 4 | D86: In Service | E86: H506 | F86: A100 | G86: H506 | H86: TRUE | I86: 45945.554 | J86: Auto Enrolment DC | L86: 602833 | M86: DC | N86: 20 | P86: SecureShare Ornua Co | Q86: DC | R86: 1 | S86: Auto Enrolment DC | T86: DC | U86: 45940.423 | V86: 45945.958 | W86: 1 | X86: 3.1318056 | Y86: ILFS Corporate Business | Z86: 25283CBPR03546B | AA86: Ornua Co-Operative Limited | AB86: Completed | AC86: x26 NEs Added | AD86: INTERNAL | AE86: 1 | AO86: TM05 | AP86: N
A87: 011966M | B87: NEBAUTO | C87: Day 2 | D87: In Service | E87: J905 | F87: NJ24 | G87: J905 | H87: TRUE | I87: 45944.353 | J87: Auto Enrolment DC | L87: 601299 | M87: DC | P87: SecureShare Thermo F | Q87: DC | R87: 1 | S87: Auto Enrolment DC | T87: DC | U87: 45940.426 | V87: 45945.958 | W87: 1 | X87: 1.9270023 | Y87: Unio (BONDS) | Z87: 25283CBPR0354A5 | AA87: Thermo Fisher Scientific Cork Limited | AB87: Completed | AC87: members have been added | AE87: 1 | AO87: TM34 | AP87: N
A88: 011972M | B88: NEBAUTO | C88: Day 4 | D88: In Service | E88: X967 | F88: A100 | G88: x967 | H88: TRUE | I88: 45945.444 | J88: Auto Enrolment DC | L88: 603409 | M88: DC | P88: SecureShare Magnet N | Q88: DC | R88: 1 | S88: Auto Enrolment DC | T88: DC | U88: 45940.428 | V88: 45945.958 | W88: 1 | X88: 3.0152894 | Y88: ILFS Corporate Business | Z88: 25283CBPR0354DF | AA88: Magnet Networks Limited | AB88: Completed | AC88: Magdalen Hepes | AD88: INTERNAL | AE88: 1 | AO88: TM07 | AP88: N
A89: 011982M | B89: NESAUTO | C89: Day 3 | D89: In Service | E89: S143 | F89: S168 | G89: S143 | H89: TRUE | I89: 45944.596 | J89: Auto Enrolment DC | K89: 1202351 | L89: 606872 | M89: DC | P89: SecureShare Ingersol | Q89: DC | R89: 1 | S89: Auto Enrolment DC | T89: DC | U89: 45940.435 | V89: 45945.958 | W89: 1 | X89: 2.1610648 | Y89: Mercer (Elect Existing Business) | Z89: 25283CBPR03556E | AA89: Ingersoll- Rand Industrial Ire. Limited | AB89: Completed | AC89: Barry mcDonald 1202351 | AD89: INTERNAL | AE89: 1 | AO89: TM01 | AP89: N
A90: 011988M | B90: NEBAUTO | C90: Day 4 | D90: In Service | E90: C192 | F90: A100 | G90: C192 | H90: TRUE | I90: 45945.651 | J90: Auto Enrolment DC | L90: 606840 | M90: DC | P90: SecureShare Booking | Q90: DC | R90: 1 | S90: Auto Enrolment DC | T90: DC | U90: 45940.435 | V90: 45945.958 | W90: 1 | X90: 3.2150926 | Y90: ILFS Corporate Business | Z90: 25283CBPR03556F | AA90: Booking Holdings Fin. Serv. Intl Ltd | AB90: Completed | AC90: Employer: OpenTable Ireland :: Number of Members: N/A | AD90: INTERNAL | AE90: 1 | AO90: TM05 | AP90: N
A91: 011991M | B91: NEBAUTO | C91: Day 2 | D91: In Service | E91: Y337 | F91: A300 | G91: Y337 | H91: TRUE | I91: 45944.392 | J91: Auto Enrolment DC | L91: 609702 | M91: DC | P91: SecureShare St Chris | Q91: DC | R91: 1 | S91: Auto Enrolment DC | T91: DC | U91: 45940.436 | V91: 45945.958 | W91: 1 | X91: 1.9558681 | Y91: ILFS Corporate Business | Z91: 25283CBPR035572 | AA91: NFVSP St Christopher's Services CLG | AB91: Completed | AC91: 1 NE N/A :: Number of Members: N/A | AD91: INTERNAL | AE91: 1 | AO91: TM32 | AP91: N
A92: 011994M | B92: NESAUTO | C92: Day 4 | D92: In Service | E92: Y337 | F92: TU84 | G92: Y337 | H92: TRUE | I92: 45945.452 | J92: Auto Enrolment DC | K92: 1202446 | L92: 609841 | M92: DC | P92: SecureShare Blackroc | Q92: DC | R92: 1 | S92: Auto Enrolment DC | T92: DC | U92: 45940.438 | V92: 45945.958 | W92: 1 | X92: 3.0144213 | Y92: Joseph G. Byrne & Sons Consulting | Z92: 25283CBPR0355B7 | AA92: Galway Clinic Doughiska Unltd Co | AB92: Completed | AC92: Anwar Paul Thomas - added 1202446 | AD92: INTERNAL | AE92: 1 | AO92: TM32 | AP92: N
A93: 011999M | B93: NEBAUTO | C93: Day 3 | D93: In Service | E93: X967 | F93: RT02 | G93: x967 | H93: TRUE | I93: 45945.433 | J93: Auto Enrolment DC | L93: 609819 | M93: DC | P93: SecureShare Magnet N | Q93: DC | R93: 1 | S93: Auto Enrolment DC | T93: DC | U93: 45940.44 | V93: 45945.958 | W93: 1 | X93: 2.9922222 | Y93: PWC Financial Consulting DAC | Z93: 25283CBPR0355EB | AA93: Enet Defined Contribution Plan | AB93: Completed | AC93: Ozgur Demirtas | AD93: INTERNAL | AE93: 1 | AO93: TM01 | AP93: N
A94: 012014M | B94: NESAUTO | C94: Day 3 | D94: In Service | E94: S143 | F94: RA51 | G94: S143 | H94: TRUE | I94: 45944.602 | J94: Auto Enrolment DC | L94: 606984 | M94: DC | P94: PPI Secure Path | Q94: DC | R94: 1 | S94: Auto Enrolment DC | T94: DC | U94: 45940.456 | V94: 45945.958 | W94: 1 | X94: 2.1460417 | Y94: Allen Retirement & Finance Ltd (a | Z94: 25283CBPR035695 | AA94: Union of the Sisters of the Presentation | AB94: Completed | AC94: Mairead Loughnane 1050849 already keyed member update copied out | AE94: 1 | AO94: TM07 | AP94: N
A95: 012015M | B95: NEBAUTO | C95: Day 3 | D95: In Service | E95: X967 | F95: A100 | G95: x967 | H95: TRUE | I95: 45945.409 | J95: Auto Enrolment DC | L95: 609621 | M95: DC | P95: SecureShare Hertz Eu | Q95: DC | R95: 1 | S95: Auto Enrolment DC | T95: DC | U95: 45940.455 | V95: 45945.958 | W95: 1 | X95: 2.9537963 | Y95: ILFS Corporate Business | Z95: 25283CBPR0356E8 | AA95: Hertz Europe Service Centre Limited | AB95: Completed | AC95: 8 x NE | AD95: INTERNAL | AE95: 1 | AO95: TM05 | AP95: N
A96: 012020M | B96: NEBAUTO | C96: Day 4 | D96: In Service | E96: Y337 | F96: A300 | G96: Y337 | H96: TRUE | I96: 45945.587 | J96: Auto Enrolment DC | L96: 603990 | M96: DC | P96: SecureShare Stryker | Q96: DC | R96: 1 | S96: Auto Enrolment DC | T96: DC | U96: 45940.456 | V96: 45945.958 | W96: 1 | X96: 3.1308102 | Y96: ILFS Corporate Business | Z96: 25283CBPR035729 | AA96: Stryker Ireland DC Pension Plan | AB96: Completed | AC96: 2 NEs N/A :: Number of Members: N/A | AD96: INTERNAL | AE96: 1 | AO96: TM32 | AP96: N
A97: 012033M | B97: NEBAUTO | C97: Day 2 | D97: In Service | E97: J905 | F97: A100 | G97: J905 | H97: TRUE | I97: 45943.486 | J97: Auto Enrolment DC | L97: 603549 | M97: DC | N97: 10 | P97: SecureShare Royal Lo | Q97: DC | R97: 1 | S97: Auto Enrolment DC | T97: DC | U97: 45940.471 | V97: 45945.958 | W97: 1 | X97: 1.0145486 | Y97: ILFS Corporate Business | Z97: 25283CBPR035803 | AA97: Royal London Mutual Ins. Society Ltd. | AB97: Completed | AC97: Employer: ‘Royal London Ireland Pension Plan :: Number of Members: N/A | AD97: INTERNAL | AE97: 1 | AO97: TM05 | AP97: N
A98: 012035M | B98: NEBAUTO | C98: Day 4 | D98: In Service | E98: C192 | F98: NJ23 | G98: C192 | H98: TRUE | I98: 45945.687 | J98: Auto Enrolment DC | L98: 602238 | M98: DC | P98: SecureShare Unio Emp | Q98: DC | R98: 1 | S98: Auto Enrolment DC | T98: DC | U98: 45940.474 | V98: 45945.958 | W98: 1 | X98: 3.212581 | Y98: Unio Ltd | Z98: 25283CBPR03583B | AA98: ActiveCampaign Ireland Limited | AB98: Completed | AC98: Employer: ActiveCampaign Ireland Lim [602238] :: Number of Members: 1 | AD98: INTERNAL | AE98: 1 | AO98: TM35 | AP98: N
A99: 012047M | B99: NESAUTO | C99: Day 3 | D99: In Service | E99: Y337 | F99: RT02 | G99: Y337 | H99: TRUE | I99: 45945.449 | J99: Auto Enrolment DC | K99: 4005561 | L99: 602631 | M99: DC | P99: SecureShare Society | Q99: DC | R99: 1 | S99: Auto Enrolment DC | T99: DC | U99: 45940.488 | V99: 45945.958 | W99: 1 | X99: 2.9612847 | Y99: PWC Financial Consulting DAC | Z99: 25283CBPR03593D | AA99: Society of Saint Vincent De Paul | AB99: Completed | AC99: Tracey Cooney - added 4005561 | AD99: INTERNAL | AE99: 1 | AO99: TM33 | AP99: N
A100: 012060M | B100: NESAUTO | C100: Day 2 | D100: In Service | E100: J987 | F100: 4056 | G100: J987 | H100: TRUE | I100: 45943.626 | J100: Auto Enrolment DC | K100: 1202032 | L100: 603473 | M100: DC | P100: SecureShare Fold Hou | Q100: DC | R100: 1 | S100: Auto Enrolment DC | T100: DC | U100: 45940.497 | V100: 45945.958 | W100: 1 | X100: 1.1290509 | Y100: Joan Brady | Z100: 25283CBPR035A53 | AA100: Fold Housing Association Ireland Ltd. | AB100: Completed | AC100: Clodagh Kierans | AD100: INTERNAL | AE100: 1 | AO100: TM05 | AP100: N
...

Sheet SQL
A2: Select b.batch_id , b.batch_name, b.creation_date as Created, b.completed_date as Completed, b.num_data_records_loaded, b.num_data_records_valid, b.num_data_records_errored, b.num_data_records_skipped, b.created_by, b.attribute4 as Midas_No, b.status From SLDBA.BATCH b Where b.creation_date >= '06-01-2025' AND b.completed_date is not Null

Sheet Notes
A1: Objective
A2: Identify the secure share submissions and number of members loaded
A3: Ideally there is one Secure Share Submission with a unique Reference Number. This data is contained within the tab IP_ORG_Usecase_Submission_Statu
A4: That Reference Number number is then used as part of the bulk upload process. The Tab "Export Spreadsheet" contains the list up uploads. The Reference number is called MIDAS_NO on this tab
A5: By matching the Reference Number submission and upload we can tell how many members were added by using the NUM_DATA_RECORDS_LOADED column
A6: On top of wanting to know how many members were loaded I want to be able to drill down by "Organization Name" too
A14: Complication
A15: There may be more than 1 upload to PPI- this is because some members will fail. So a portion is loaded, Then another uploaded is done for the balance, but this also uses the same unique midas number
A16: If we take October as a reference there was only 2 such instances.
A19: IP_Org_Usecase_Submission_Statu
A20: Use Case Name | B20: Only Add members in scope
A21: Submission Status | B21: Only completed in scope
A22: I then do a look up of the Midas completed workitems (see Tableau single and bulk) to determine if it was single or bulk update
A23: I also do a check to determine the number of members loaded via PPI by checking the midas number v the Export Sheet (sharpload data)
A25: IP_Org_Usecase_Submission_Statu
A26: COMPLETED | B26: Not in date order so I ordered it
B27: I deleted everything pre 1st Oct | C27: I done this as submission data was only for Oct
A29: Tableau Single & Bulk
A30: This is just a downloaded of New Entrant Single and Bulk Workitems completed on Midas
